Workbook

Sheet BO
A1: Estado do Rio Grande do Sul
A2: MUNICÍPIO DE INDEPENDÊNCIA
A3: DEMONSTRAÇÕES CONTÁBEIS CONSOLIDADAS
F4: CNPJ | G4: 12.091.144/0001-80
A5: BALANÇO ORÇAMENTÁRIO
F6: Exercício: | G6: 2015
A8: Quadro Principal
A9: RECEITAS ORÇAMENTÁRIAS | B9: Previsão Inicial (a) | C9: Previsão Atualizada (b) | D9: Receitas Realizadas ( c) | E9: SALDO (d) = (c-b)
A10: Receitas Correntes (I) | B10: =SUM(B11:B18) -> 0 | C10: =SUM(C11:C18) -> 0 | D10: =SUM(D11:D18) -> 0 | E10: =D10-C10 -> 0
A11: Receita Tributária | E11: =D11-C11 -> 0
A12: Receita de Contribuições | E12: =D12-C12 -> 0
A13: Receita Patrimonial | E13: =D13-C13 -> 0
A14: Receita Agropecuária | E14: =D14-C14 -> 0
A15: Receita Industrial | E15: =D15-C15 -> 0
A16: Receita de Serviços | E16: =D16-C16 -> 0
A17: Transferências Correntes | E17: =D17-C17 -> 0
A18: Outras Receitas Correntes | E18: =D18-C18 -> 0
A19: Receitas de Capital (II) | B19: =SUM(B20:B24) -> 0 | C19: =SUM(C20:C24) -> 0 | D19: =SUM(D20:D24) -> 0 | E19: =D19-C19 -> 0
A20: Operações de Crédito | E20: =D20-C20 -> 0
A21: Alienação de Bens | E21: =D21-C21 -> 0
A22: Amortizações de Empréstimos | E22: =D22-C22 -> 0
A23: Transferências de Capital | E23: =D23-C23 -> 0
A24: Outras Receitas de Capital | E24: =D24-C24 -> 0
A25: Recursos Arrecadados em Exercícios Anteriores (III) | E25: =D25-C25 -> 0
A26: SUBTOTAL DAS RECEITAS (IV) = (I + II + III) | B26: =B10+B19+B25 -> 0 | C26: =C10+C19+C25 -> 0 | D26: =D10+D19+D25 -> 0 | E26: =D26-C26 -> 0
A27: Operações de Crédito/ Refinanciamento (V) | B27: =B28+B31 -> 0 | C27: =C28+C31 -> 0 | D27: =D28+D31 -> 0 | E27: =D27-C27 -> 0
A28: Operações de Crédito Internas | B28: =SUM(B29:B30) -> 0 | C28: =SUM(C29:C30) -> 0 | D28: =SUM(D29:D30) -> 0 | E28: =D28-C28 -> 0
A29: Mobiliária | E29: =D29-C29 -> 0
A30: Contratual | E30: =D30-C30 -> 0
A31: Operações de Crédito Externas | B31: =SUM(B32:B33) -> 0 | E31: =D31-C31 -> 0
A32: Mobiliária | E32: =D32-C32 -> 0
A33: Contratual | E33: =D33-C33 -> 0
A34: SUBTOTAL COM REFINANCIAMENTO (VI) = (IV + V) | B34: =B26+B27 -> 0 | C34: =C26+C27 -> 0 | D34: =D26+D27 -> 0 | E34: =D34-C34 -> 0
A35: Déficit (VII) | B35: =IF(B34<B60,B60-B34,0) -> 0 | C35: =IF(C34<C60,C60-C34,0) -> 0 | D35: =IF(D34<D60,D60-D34,0) -> 0 | E35: =D35-C35 -> 0
A36: TOTAL (VIII) = (VI + VII) | B36: =B34+B35 -> 0 | C36: =C34+C35 -> 0 | D36: =D34+D35 -> 0 | E36: =D36-C36 -> 0
A37: Saldos de Exercícios Anteriores (Utilizados Para Créditos Adicionais) | B37: =SUM(B38:B39) -> 0 | C37: =SUM(C38:C39) -> 0 | D37: =SUM(D38:D39) -> 0 | E37: =D37-C37 -> 0
A38: Superávit Financeiro | E38: =D38-C38 -> 0
A39: Reabertura de Créditos Adicionais | E39: =D39-C39 -> 0
A41: DESPESAS ORÇAMENTÁRIAS | B41: Dotação Inicial (e) | C41: Dotação Atualizada (f) | D41: Despesas Empenhadas (g) | E41: Despesas Liquidadas (h) | F41: Despesas Pagas (i) | G41: Saldo da Dotação (j) = (f-g)
A42: Despesas Correntes (IX) | B42: =SUM(B43:B45) -> 0 | C42: =SUM(C43:C45) -> 0 | D42: =SUM(D43:D45) -> 0 | E42: =SUM(E43:E45) -> 0 | F42: =SUM(F43:F45) -> 0 | G42: =C42-D42 -> 0
A43: Pessoal e Encargos Sociais | G43: =C43-D43 -> 0
A44: Juros e Encargos da Dívida | G44: =C44-D44 -> 0
A45: Outras Despesas Correntes | G45: =C45-D45 -> 0
A46: Despesas de Capital (X) | B46: =SUM(B47:B49) -> 0 | C46: =SUM(C47:C49) -> 0 | D46: =SUM(D47:D49) -> 0 | E46: =SUM(E47:E49) -> 0 | F46: =SUM(F47:F49) -> 0 | G46: =C46-D46 -> 0
A47: Investimentos | G47: =C47-D47 -> 0
A48: Inversões Financeiras | G48: =C48-D48 -> 0
A49: Amortização da Dívida | G49: =C49-D49 -> 0
A50: Reserva de Contingência (XI) | G50: =C50-D50 -> 0
A51: Reserva do RPPS (XII) | G51: =C51-D51 -> 0
A52: SUBTOTAL DAS DESPESAS (XIII) = (IX + X + XI + XII) | B52: =B42+B46+B50+B51 -> 0 | C52: =C42+C46+C50+C51 -> 0 | D52: =D42+D46+D50+D51 -> 0 | E52: =E42+E46+E50+E51 -> 0 | F52: =F42+F46+F50+F51 -> 0 | G52: =C52-D52 -> 0
A53: Amortização da Dívida / Refinanciamento (XIV) | B53: =B54+B57 -> 0 | C53: =C54+C57 -> 0 | D53: =D54+D57 -> 0 | E53: =E54+E57 -> 0 | F53: =F54+F57 -> 0 | G53: =C53-D53 -> 0
A54: Amortização da Dívida Interna | B54: =SUM(B55:B56) -> 0 | C54: =SUM(C55:C56) -> 0 | D54: =SUM(D55:D56) -> 0 | E54: =SUM(E55:E56) -> 0 | F54: =SUM(F55:F56) -> 0 | G54: =C54-D54 -> 0
A55: Dívida Mobiliária | G55: =C55-D55 -> 0
A56: Outras Dívidas | G56: =C56-D56 -> 0
A57: Amortização da Dívida Externa | B57: =SUM(B58:B59) -> 0 | C57: =SUM(C58:C59) -> 0 | D57: =SUM(D58:D59) -> 0 | E57: =SUM(E58:E59) -> 0 | F57: =SUM(F58:F59) -> 0 | G57: =C57-D57 -> 0
A58: Dívida Mobiliária | G58: =C58-D58 -> 0
A59: Outras Dívidas | G59: =C59-D59 -> 0
A60: SUBTOTAL COM REFINANCIAMENTO (XV)= (XIII+ XIV) | B60: =B52+B53 -> 0 | C60: =C52+C53 -> 0 | D60: =D52+D53 -> 0 | E60: =E52+E53 -> 0 | F60: =F52+F53 -> 0 | G60: =C60-D60 -> 0
A61: Superávit (XVI) | B61: =IF(B60<B34,B34-B60,0) -> 0 | C61: =IF(C60<C34,C34-C60,0) -> 0 | D61: =IF(D60<D34,D34-D60,0) -> 0 | E61: =IF(E60<D34,D34-E60,0) -> 0 | F61: =IF(F60<D34,D34-F60,0) -> 0
A62: TOTAL (XVII) = (XV + XVI) | B62: =B60+B61 -> 0 | C62: =C60+C61 -> 0 | D62: =D60+D61 -> 0 | E62: =E60+E61 -> 0 | F62: =F60+F61 -> 0
A64: Quadro da Execução dos Restos a Pagar Não Processados
A65: RESTOS A PAGAR NÃO PROCESSADOS | B65: Inscritos | D65: Liquidados (c) | E65: Pagos (d) | F65: Cancelados (e) | G65: Saldo f= (a+b-d-e)
B66: Em Exercícios Anteriores (a) | C66: Em 31 de Dezembro do Exercício Anterior (b)
A67: Despesas Correntes | B67: =SUM(B68:B70) -> 0 | C67: =SUM(C68:C70) -> 0 | D67: =SUM(D68:D70) -> 0 | E67: =SUM(E68:E70) -> 0 | F67: =SUM(F68:F70) -> 0 | G67: =B67+C67-E67-F67 -> 0
A68: Pessoal E Encargos Sociais | G68: =B68+C68-E68-F68 -> 0
A69: Juros E Encargos Da Dívida | G69: =B69+C69-E69-F69 -> 0
A70: Outras Despesas Correntes | G70: =B70+C70-E70-F70 -> 0
A71: Despesas De Capital | B71: =SUM(B72:B74) -> 0 | C71: =SUM(C72:C74) -> 0 | D71: =SUM(D72:D74) -> 0 | E71: =SUM(E72:E74) -> 0 | F71: =SUM(F72:F74) -> 0 | G71: =B71+C71-E71-F71 -> 0
A72: Investimentos | G72: =B72+C72-E72-F72 -> 0
A73: Inversões Financeiras | G73: =B73+C73-E73-F73 -> 0
A74: Amortização Da Dívida | G74: =B74+C74-E74-F74 -> 0
A75: TOTAL | B75: =B67+B71 -> 0 | C75: =C67+C71 -> 0 | D75: =D67+D71 -> 0 | E75: =E67+E71 -> 0 | F75: =F67+F71 -> 0 | G75: =B75+C75-E75-F75 -> 0
A77: Quadro da Execução dos Restos a Pagar Processados e Restos a Pagar Não Processados Liquidados
A78: RESTOS A PAGAR PROCESSADOS E RESTOS A PAGAR NÃO PROCESSADOS LIQUIDADOS | B78: INSCRITOS | D78: PAGOS (c) | E78: CANCELADOS (d) | F78: SALDO f= (a+b-c-d)
B79: EM EXERCÍCIOS ANTERIORES (a) | C79: EM 31 DE DEZEMBRO DO EXERCÍCIO ANTERIOR (b)
A80: Despesas Correntes | B80: =SUM(B81:B83) -> 0 | C80: =SUM(C81:C83) -> 0 | D80: =SUM(D81:D83) -> 0 | E80: =SUM(E81:E83) -> 0 | F80: =B80+C80-D80-E80 -> 0
A81: Pessoal E Encargos Sociais | F81: =B81+C81-D81-E81 -> 0
A82: Juros E Encargos Da Dívida | F82: =B82+C82-D82-E82 -> 0
A83: Outras Despesas Correntes | F83: =B83+C83-D83-E83 -> 0
A84: Despesas De Capital | B84: =SUM(B85:B87) -> 0 | C84: =SUM(C85:C87) -> 0 | D84: =SUM(D85:D87) -> 0 | E84: =SUM(E85:E87) -> 0 | F84: =B84+C84-D84-E84 -> 0
A85: Investimentos | F85: =B85+C85-D85-E85 -> 0
A86: Inversões Financeiras | F86: =B86+C86-D86-E86 -> 0
A87: Amortização Da Dívida | F87: =B87+C87-D87-E87 -> 0
A88: TOTAL | B88: =B80+B84 -> 0 | C88: =C80+C84 -> 0 | D88: =D80+D84 -> 0 | E88: =E80+E84 -> 0 | F88: =B88+C88-D88-E88 -> 0

Sheet BF
A1: =BO!A1 -> Estado do Rio Grande do Sul
A2: =BO!A2 -> MUNICÍPIO DE INDEPENDÊNCIA
A3: =BO!A3 -> DEMONSTRAÇÕES CONTÁBEIS CONSOLIDADAS
F4: CNPJ | G4: =BO!G4 -> 12.091.144/0001-80
A5: BALANÇO FINANCEIRO
F6: Exercício: | G6: =BO!G6 -> 2015
A8: Quadro Principal
A9: INGRESSOS | E9: DISPÊNDIOS
A10: ESPECIFICAÇÃO | B10: Exercício Atual | C10: Exercício Anterior | E10: ESPECIFICAÇÃO | F10: Exercício Atual | G10: Exercício Anterior
A11: Receita Orçamentária (I) | B11: =B12+B13 -> 0 | C11: =C12+C13 -> 0 | E11: Despesa Orçamentária (VI) | F11: =F12+F13 -> 0 | G11: =G12+G13 -> 0
A12: Ordinária | E12: Ordinária
A13: Vinculada | B13: =SUM(B14:B19) -> 0 | C13: =SUM(C14:C19) -> 0 | E13: Vinculada | F13: =SUM(F14:F19) -> 0 | G13: =SUM(G14:G19) -> 0
A14: Recursos Vinculados à Educação | E14: Recursos Destinados à Educação
A15: Recursos Vinculados à Saúde | E15: Recursos Destinados à Saúde
A16: Recursos Vinculados à Previdência Social - RPPS | E16: Recursos Destinado a Previdência Social - RPPS
A17: Recursos Vinculados à Previdência Social - RGPS | E17: Recursos Destinado a Previdência Social - RGPS
A18: Recursos Vinculados à Seguridade Social | E18: Recursos Destinado a Seguridade Social
A19: Outras Destinações de Recursos | E19: Outras Destinações de Recursos
A20: Transferências Financeiras Recebidas (II) | B20: =SUM(B21:B24) -> 0 | C20: =SUM(C21:C24) -> 0 | E20: Transferências Financeiras Concedidas (VII) | F20: =SUM(F21:F24) -> 0 | G20: =SUM(G21:G24) -> 0
A21: Transferências Recebidas para a Execução Orçamentária | E21: Transferências Concedidas para a Execução Orçamentária
A22: Transferências Recebidas Independentes de Execução Orçamentária | E22: Transferências Concedidas Independentes de Execução Orçamentária
A23: Transferências Recebidas para Aportes de recursos para o RPPS | E23: Transferências Concedidas para Aportes de recursos para o RPPS
A24: Transferências Recebidas para Aportes de recursos para o RGPS | E24: Transferências Concedidas para Aportes de recursos para o RGPS
A25: Recebimentos Extraorçamentários (III) | B25: =SUM(B26:B29) -> 0 | C25: =SUM(C26:C29) -> 0 | E25: Pagamentos Extraorçamentários (VIII) | F25: =SUM(F26:F29) -> 0 | G25: =SUM(G26:G29) -> 0
A26: Inscrição de Restos a Pagar Não Processados | E26: Pagamentos de Restos a Pagar Não Processados
A27: Inscrição de Restos a Pagar Processados | E27: Pagamentos de Restos a Pagar Processados
A28: Depósitos Restituíveis e Valores Vinculados | E28: Depósitos Restituíveis e Valores Vinculados
A29: Outros Recebimentos Extraorçamentários | E29: Outros Pagamentos Extraorçamentários
A30: Saldo do Exercício Anterior (IV) | B30: =SUM(B31:B33) -> 0 | C30: =SUM(C31:C33) -> 0 | E30: Saldo para o Exercício Seguinte (IX) | F30: =SUM(F31:F33) -> 0 | G30: =SUM(G31:G33) -> 0
A31: Caixa e Equivalentes de Caixa | E31: Caixa e Equivalentes de Caixa
A32: Depósitos Restituíveis e Valores Vinculados | E32: Depósitos Restituíveis e Valores Vinculados
A33: Investimentos e Aplicações Temporárias a Curto Prazo | E33: Investimentos e Aplicações Temporárias a Curto Prazo
A34: TOTAL (V) = (I+II+III+IV) | B34: =B11+B20+B25+B30 -> 0 | C34: =C11+C20+C25+C30 -> 0 | E34: TOTAL (X) = (VI+VII+VIII+IX) | F34: =F11+F20+F25+F30 -> 0 | G34: =G11+G20+G25+G30 -> 0
A36: Quadro Anexo
A37: ESPECIFICAÇÃO | B37: Exercício Atual | E37: Exercício Anterior
B38: Receita Orçamentária | C38: Deduções da Receita Orçamentária | D38: Saldo | E38: Receita Orçamentária | F38: Deduções da Receita Orçamentária | G38: Saldo
B39: (a) | C39: (b) | D39: (c) = (a - b) | E39: (d) | F39: (e) | G39: (f) = (d - e)
A40: Ordinária | D40: =B40-C40 -> 0 | G40: =E40-F40 -> 0
A41: Vinculada | B41: =SUM(B42:B47) -> 0 | C41: =SUM(C42:C47) -> 0 | D41: =SUM(D42:D47) -> 0 | E41: =SUM(E42:E47) -> 0 | F41: =SUM(F42:F47) -> 0 | G41: =SUM(G42:G47) -> 0
A42: Recursos Vinculados à Educação | D42: =B42-C42 -> 0 | G42: =E42-F42 -> 0
A43: Recursos Vinculados à Saúde | D43: =B43-C43 -> 0 | G43: =E43-F43 -> 0
A44: Recursos Vinculados à Previdência Social - RPPS | D44: =B44-C44 -> 0 | G44: =E44-F44 -> 0
A45: Recursos Vinculados à Previdência Social - RGPS | D45: =B45-C45 -> 0 | G45: =E45-F45 -> 0
A46: Recursos Vinculados à Seguridade Social | D46: =B46-C46 -> 0 | G46: =E46-F46 -> 0
A47: Outras Destinações de Recursos | D47: =B47-C47 -> 0 | G47: =E47-F47 -> 0
A48: TOTAL | B48: =B40+B41 -> 0 | C48: =C40+C41 -> 0 | D48: =D40+D41 -> 0 | E48: =E40+E41 -> 0 | F48: =F40+F41 -> 0 | G48: =G40+G41 -> 0

Sheet BP
A1: =BO!A1 -> Estado do Rio Grande do Sul
A2: =BO!A2 -> MUNICÍPIO DE INDEPENDÊNCIA
A3: =BO!A3 -> DEMONSTRAÇÕES CONTÁBEIS CONSOLIDADAS
B4: CNPJ | C4: =BO!G4 -> 12.091.144/0001-80
A5: BALANÇO PATRIMONIAL
B6: Exercício: | C6: =BO!G6 -> 2015
A8: Quadro Principal
A9: Campo | B9: Exercício Atual | C9: Exercício Anterior
A10: ATIVO | B10: =B11+B17 -> 0 | C10: =C11+C17 -> 0
A11: Ativo Circulante | B11: =SUM(B12:B16) -> 0 | C11: =SUM(C12:C16) -> 0
A12: Caixa e Equivalentes de Caixa
A13: Créditos a Curto Prazo
A14: Investimentos e Aplicações Temporárias a Curto Prazo
A15: Estoques
A16: VPD Pagas Antecipadamente
A17: Ativo Não Circulante | B17: =B18+B23+B24+B25+B26 -> 0 | C17: =C18+C23+C24+C25+C26 -> 0
A18: Realizável a Longo Prazo | B18: =SUM(B19:B22) -> 0 | C18: =SUM(C19:C22) -> 0
A19: Créditos a Longo Prazo
A20: Investimentos Temporários a Longo Prazo
A21: Estoques
A22: VPD pagas antecipadamente
A23: Investimentos
A24: Imobilizado
A25: Intangível
A26: Diferido
A27: PASSIVO E PATRIMÔNIO LÍQUIDO | B27: =B28+B36+B44 -> 0 | C27: =C28+C36+C44 -> 0
A28: Passivo Circulante | B28: =SUM(B29:B35) -> 0 | C28: =SUM(C29:C35) -> 0
A29: Obrigações Trabalhistas, Previdenciárias e Assistenciais a Pagar a Curto Prazo
A30: Empréstimos e Financiamentos a Curto Prazo
A31: Fornecedores e Contas a Pagar a Curto Prazo
A32: Obrigações Fiscais a Curto Prazo
A33: Obrigações de Repartições a Outros Entes
A34: Provisões a Curto Prazo
A35: Demais Obrigações a Curto Prazo
A36: Passivo Não Circulante | B36: =SUM(B37:B43) -> 0 | C36: =SUM(C37:C43) -> 0
A37: Obrigações Trabalhistas, Previdenciárias e Assistenciais a Pagar a Longo Prazo
A38: Empréstimos e Financiamentos a Longo Prazo
A39: Fornecedores e Contas a Pagar a Longo Prazo
A40: Obrigações Fiscais a Longo Prazo
A41: Provisões a Longo Prazo
A42: Demais Obrigações a Longo Prazo
A43: Resultado Diferido
A44: Patrimônio Líquido | B44: =SUM(B45:B52) -> 0 | C44: =SUM(C45:C52) -> 0
A45: Patrimônio Social e Capital Social
A46: Adiantamento Para Futuro Aumento de Capital
A47: Reservas de Capital
A48: Ajustes de Avaliação Patrimonial
A49: Reservas de Lucros
A50: Demais Reservas
A51: Resultados Acumulados
A52: (-) Ações / Cotas em Tesouraria
A54: Quadro dos Ativos e Passivos Financeiros e Permanentes
A55: Campo | B55: Exercício Atual | C55: Exercício Anterior
A56: ATIVO | B56: =B57+B58 -> 0 | C56: =C57+C58 -> 0
A57: Ativo Financeiro
A58: Ativo Permanente
A59: PASSIVO | B59: =B60+B61 -> 0 | C59: =C60+C61 -> 0
A60: Passivo Financeiro
A61: Passivo Permanente
A62: Saldo Patrimonial | B62: =B56-B61 -> 0 | C62: =C56-C61 -> 0
A64: Quadro das Contas de Compensação
A65: Campo | B65: Exercício Atual | C65: Exercício Anterior
A66: Atos Potenciais Ativos | B66: =SUM(B67:B70) -> 0 | C66: =SUM(C67:C70) -> 0
A67: Garantias e Contra garantias recebidas
A68: Direitos Conveniados e outros instrumentos congêneres
A69: Direitos Contratuais
A70: Outros atos potenciais ativos
A71: Atos Potenciais Passivos | B71: =SUM(B72:B75) -> 0 | C71: =SUM(C72:C75) -> 440580.88
A72: Garantias e Contra garantias concedidas
A73: Obrigações conveniadas e outros instrumentos congêneres
A74: Obrigações contratuais
A75: Outros atos potenciais passivos | C75: 440580.88
A77: Quadro do Superávit / Déficit Financeiro
A78: Fonte de Recurso | B78: Exercício Atual | C78: Exercício Anterior
A79: 0001 LIVRE
A80: 0020 MDE
A81: 0031 FUNDEB
A82: 0040 ASPS
A83: 0050 RPPS
A114: Total | B114: =SUM(B79:B113) -> 0 | C114: =SUM(C79:C113) -> 0

Sheet DVP
A1: =BO!A1 -> Estado do Rio Grande do Sul
A2: =BO!A2 -> MUNICÍPIO DE INDEPENDÊNCIA
A3: =BO!A3 -> DEMONSTRAÇÕES CONTÁBEIS CONSOLIDADAS
A4: CNPJ | B4: =BO!G4 -> 12.091.144/0001-80
A5: DEMONSTRAÇÃO DAS VARIAÇÕES PATRIMONIAIS
B6: Exercício: | C6: =BO!G6 -> 2015
A8: Conta | B8: Exercício Atual | C8: Exercício Anterior
A9: VARIAÇÕES PATRIMONIAIS AUMENTATIVAS | B9: =B10+B14+B19+B23+B30+B40+B46 -> 0 | C9: =C10+C14+C19+C23+C30+C40+C46 -> 0
A10: Impostos, Taxas e Contribuições de Melhoria | B10: =SUM(B11:B13) -> 0 | C10: =SUM(C11:C13) -> 0
A11: Impostos
A12: Taxas
A13: Contribuições de Melhoria
A14: Contribuições | B14: =SUM(B15:B18) -> 0 | C14: =SUM(C15:C18) -> 0
A15: Contribuições Sociais
A16: Contribuições de Intervenção no domínio econômico
A17: Contribuição de Iluminação Pública
A18: Contribuições de Interesse das Categorias Profissionais
A19: Exploração e Venda de Bens, Serviços e Direitos | B19: =SUM(B20:B22) -> 0 | C19: =SUM(C20:C22) -> 0
A20: Venda de Mercadorias
A21: Venda de Produtos
A22: Exploração de Bens e Direitos e Prestação de Serviços
A23: Variações Patrimoniais Aumentativas Financeiras | B23: =SUM(B24:B29) -> 0 | C23: =SUM(C24:C29) -> 0
A24: Juros e Encargos de Empréstimos e Financiamentos Concedidos
A25: Juros e Encargos de Mora
A26: Variações Monetárias e Cambiais
A27: Descontos Financeiros Obtidos
A28: Remuneração de Depósitos Bancários e Aplicações Financeiras
A29: Outras Variações Patrimoniais Aumentativas – Financeiras
A30: Transferências e Delegações Recebidas | B30: =SUM(B31:B39) -> 0 | C30: =SUM(C31:C39) -> 0
A31: Transferências Intragovernamentais
A32: Transferências Intergovernamentais
A33: Transferências das Instituições Privadas
A34: Transferências das Instituições Multigovernamentais
A35: Transferências de Consórcios Públicos
A36: Transferências do Exterior
A37: Execução Orçamentária Delegada de Entes
A38: Transferências de Pessoas Físicas
A39: Outras Transferências e Delegações Recebidas
A40: Valorização e Ganhos com Ativos e Desincorporação de Passivos | B40: =SUM(B41:B45) -> 0 | C40: =SUM(C41:C45) -> 0
A41: Reavaliação de Ativos
A42: Ganhos com Alienação
A43: Ganhos com Incorporação de Ativos
A44: Ganhos com Desincorporação de Passivos
A45: Reversão de Redução ao Valor Recuperável
A46: Outras Variações Patrimoniais Aumentativas | B46: =SUM(B47:B50) -> 0 | C46: =SUM(C47:C50) -> 0
A47: Variação Patrimonial Aumentativa a Classificar
A48: Resultado Positivo de Participações
A49: Reversão de Provisões e Ajustes de Perdas
A50: Diversas Variações Patrimoniais Aumentativas
A52: VARIAÇÕES PATRIMONIAIS DIMINUTIVAS | B52: =B53+B58+B65+B69+B75+B84+B90+B93+B97 -> 0 | C52: =C53+C58+C65+C69+C75+C84+C90+C93+C97 -> 0
A53: Pessoal e Encargos | B53: =SUM(B54:B57) -> 0 | C53: =SUM(C54:C57) -> 0
A54: Remuneração a Pessoal
A55: Encargos Patronais
A56: Benefícios a Pessoal
A57: Outras Variações Patrimoniais Diminutivas - Pessoal e Encargos
A58: Benefícios Previdenciários e Assistenciais | B58: =SUM(B59:B64) -> 0 | C58: =SUM(C59:C64) -> 0
A59: Aposentadorias e Reformas
A60: Pensões
A61: Benefícios de Prestação Continuada
A62: Benefícios Eventuais
A63: Políticas Públicas de Transferência de Renda
A64: Outros Benefícios Previdenciários e Assistenciais
A65: Uso de Bens, Serviços e Consumo de Capital Fixo | B65: =SUM(B66:B68) -> 0 | C65: =SUM(C66:C68) -> 0
A66: Uso de material de consumo
A67: Serviços
A68: Depreciação, Amortização e Exaustão
A69: Variações Patrimoniais Diminutivas Financeiras | B69: =SUM(B70:B74) -> 0 | C69: =SUM(C70:C74) -> 0
A70: Juros e Encargos de Empréstimos e Financiamentos Obtidos
A71: Juros e Encargos de Mora
A72: Variações Monetárias e Cambiais
A73: Descontos Financeiros Concedidos
A74: Outras Variações Patrimoniais Diminutivas – Financeiras
A75: Transferências e Delegações Concedidas | B75: =SUM(B76:B83) -> 0 | C75: =SUM(C76:C83) -> 0
A76: Transferências Intragovernamentais
A77: Transferências Intergovernamentais
A78: Transferências a Instituições Privadas
A79: Transferências a Instituições Multigovernamentais
A80: Transferências a Consórcios Públicos
A81: Transferências ao Exterior
A82: Execução Orçamentária Delegada a Entes
A83: Outras Transferências e Delegações Concedidas
A84: Desvalorização e Perda de Ativos e Incorporação de Passivos | B84: =SUM(B85:B89) -> 0 | C84: =SUM(C85:C89) -> 0
A85: Reavaliação, Redução a Valor Recuperável e Ajuste para Perdas
A86: Perdas com Alienação
A87: Perdas Involuntárias
A88: Incorporação de Passivos
A89: Desincorporação de Ativos
A90: Tributárias | B90: =SUM(B91:B92) -> 0 | C90: =SUM(C91:C92) -> 0
A91: Impostos, Taxas e Contribuições de Melhoria
A92: Contribuições
A93: Custo das Mercadorias e dos Produtos Vendidos, e dos Serviços Prestados | B93: =SUM(B94:B96) -> 0 | C93: =SUM(C94:C96) -> 0
A94: Custo das Mercadorias Vendidas
A95: Custo dos Produtos Vendidos
A96: Custo dos Serviços Prestados
A97: Outras Variações Patrimoniais Diminutivas | B97: =SUM(B98:B104) -> 0 | C97: =SUM(C98:C104) -> 0
A98: Premiações
A99: Resultado Negativo de Participações
A100: Incentivos
A101: Subvenções Econômicas
A102: Participações e Contribuições
...

Sheet DFC
A1: =BO!A1 -> Estado do Rio Grande do Sul
A2: =BO!A2 -> MUNICÍPIO DE INDEPENDÊNCIA
A3: =BO!A3 -> DEMONSTRAÇÕES CONTÁBEIS CONSOLIDADAS
B4: CNPJ | C4: =BO!G4 -> 12.091.144/0001-80
A5: DEMONSTRAÇÃO DO FLUXO DE CAIXA
B6: Exercício: | C6: =BO!G6 -> 2015
A8: Campo | B8: Exercício Atual | C8: Exercício Anterior
A9: FLUXOS DE CAIXA DAS ATIVIDADES OPERACIONAIS (I) | B9: =B10-B29 -> 0 | C9: =C10-C29 -> 0
A10: Ingressos | B10: =B11+B20+B27 -> 0 | C10: =C11+C20+C27 -> 0
A11: Receitas derivadas e originárias | B11: =SUM(B12:B19) -> 0 | C11: =SUM(C12:C19) -> 0
A12: Receita Tributária
A13: Receita de Contribuições
A14: Receita Patrimonial
A15: Receita Agropecuária
A16: Receita Industrial
A17: Receita de Serviços
A18: Remuneração das Disponibilidades
A19: Outras Receitas Derivadas e Originárias
A20: Transferências correntes recebidas | B20: =B21+B25+B26 -> 0 | C20: =C21+C25+C26 -> 0
A21: Intergovernamentais | B21: =SUM(B22:B24) -> 0 | C21: =SUM(C22:C24) -> 0
A22: da União
A23: de Estados e Distrito Federal
A24: de Municípios
A25: Intragovernamentais
A26: Outras transferências correntes recebidas
A27: Outros ingressos operacionais
A28: Desembolsos | B28: =B29+B58+B62+B69 -> 0 | C28: =C29+C58+C62+C69 -> 0
A29: Pessoal e demais despesas | B29: =SUM(B30:B57) -> 0 | C29: =SUM(C30:C57) -> 0
A30: Legislativa
A31: Judiciária
A32: Essencial à Justiça
A33: Administração
A34: Defesa Nacional
A35: Segurança Pública
A36: Relações Exteriores
A37: Assistência Social
A38: Previdência Social
A39: Saúde
A40: Trabalho
A41: Educação
... A57: Encargos Especiais
A58: Juros e encargos da dívida | B58: =SUM(B59:B61) -> 0 | C58: =SUM(C59:C61) -> 0
A59: Juros e Correção Monetária da Dívida Interna
A60: Juros e Correção Monetária da Dívida Externa
A61: Outros Encargos da Dívida
A62: Transferências concedidas | B62: =B63+B67+B68 -> 0 | C62: =C63+C67+C68 -> 0
A63: Intergovernamentais | B63: =SUM(B64:B66) -> 0 | C63: =SUM(C64:C66) -> 0
A64: a União
A65: a Estados e Distrito Federal
A66: a Municípios
A67: Intragovernamentais
A68: Outras transferências concedidas
A69: Outros desembolsos operacionais
A70: FLUXOS DE CAIXA DAS ATIVIDADES DE INVESTIMENTO (II) | B70: =B71-B75 -> 0 | C70: =C71-C75 -> 0
A71: Ingressos | B71: =SUM(B72:B74) -> 0 | C71: =SUM(C72:C74) -> 0
A72: Alienação de bens
A73: Amortização de empréstimos e financiamentos concedidos
A74: Outros ingressos de investimentos
A75: Desembolsos | B75: =SUM(B76:B78) -> 0 | C75: =SUM(C76:C78) -> 0
A76: Aquisição de ativo não circulante
A77: Concessão de empréstimos e financiamentos
A78: Outros desembolsos de investimentos
A79: FLUXOS DE CAIXA DAS ATIVIDADES DE FINANCIAMENTO (III) | B79: =B80-B85 -> 0 | C79: =C80-C85 -> 0
A80: Ingressos | B80: =SUM(B81:B84) -> 0 | C80: =SUM(C81:C84) -> 0
A81: Operações de crédito
A82: Integralização do capital social de empresas dependentes
A83: Transferências de capital recebidas
A84: Outros ingressos de financiamentos
A85: Desembolsos | B85: =SUM(B86:B87) -> 0 | C85: =SUM(C86:C87) -> 0
A86: Amortização / Refinanciamento da dívida
A87: Outros desembolsos de financiamentos
A88: GERAÇÃO LÍQUIDA DE CAIXA E EQUIVALENTE DE CAIXA (I+II+III) | B88: =B9+B70+B79 -> 0 | C88: =C9+C70+C79 -> 0
A89: Caixa e equivalente de caixa inicial
A90: Caixa e equivalente de caixa final

Sheet Consistência
A1: Teste | B1: Valor 1 | C1: Valor 2 | D1: Diferença
A2: Caixa inicial da DFC = Caixa final do ano anterior da DFC | B2: =DFC!B89 -> 0 | C2: =DFC!C90 -> 0 | D2: =B2-C2 -> 0
A3: Caixa inicial da DFC = Caixa inicial do BF | B3: =DFC!B89 -> 0 | C3: =BF!B30 -> 0 | D3: =B3-C3 -> 0
A4: Caixa final da DFC = Caixa final do BF | B4: =DFC!B90 -> 0 | C4: =BF!F30 -> 0 | D4: =B4-C4 -> 0
A5: Caixa final da DFC (informado) = Caixa final da DFC (calculado) | B5: =DFC!B90 -> 0 | C5: =DFC!B89+DFC!B10-DFC!B28+DFC!B71-DFC!B75+DFC!B80-DFC!B85 -> 0 | D5: =B5-C5 -> 0
A6: Caixa final da DFC = Caixa + Investimentos do BP | B6: =DFC!B90 -> 0 | C6: =BP!B12+BP!B14+BP!B20 -> 0 | D6: =B6-C6 -> 0
A7: Caixa inicial da DFC = Caixa + Investimentos do BP (ano anterior) | B7: =DFC!B89 -> 0 | C7: =BP!C12+BP!C14+BP!C20 -> 0 | D7: =B7-C7 -> 0
A8: VPA - VPD da DVP + Resultados Acumulados do ano anterior do BP = Resultados Acumulados do BP | B8: =DVP!B9-DVP!B52+BP!C51 -> 0 | C8: =BP!B51 -> 0 | D8: =B8-C8 -> 0
A9: Ativo Financeiro - Passivo Financeiro do BP = Superávit financeiro do BP | B9: =BP!B57-BP!B60 -> 0 | C9: =BP!B114 -> 0 | D9: =B9-C9 -> 0
A10: Ativo do BP = Passivo e PL do BP | B10: =BP!B10 -> 0 | C10: =BP!B27 -> 0 | D10: =B10-C10 -> 0
A11: Ativo do BP (ano anterior) = Passivo e PL do BP (ano anterior) | B11: =BP!C10 -> 0 | C11: =BP!C27 -> 0 | D11: =B11-C11 -> 0
A12: Ativo do BP = Ativo Financeiro + Ativo Permanente do BP | B12: =BP!B10 -> 0 | C12: =BP!B56 -> 0 | D12: =B12-C12 -> 0
A13: Passivo do BP = Passivo Financeiro + Passivo Permanente do BP | B13: =BP!B28+BP!B36 -> 0 | C13: =BP!B60+BP!B61 -> 0 | D13: =B13-C13 -> 0
A14: Receita Orçamentária do BF = Receita Orçamentária do BO | B14: =BF!B11 -> 0 | C14: =BO!D34 -> 0 | D14: =B14-C14 -> 0
A15: Despesa Empenhada do BF = Despesa Empenhada do BO | B15: =BF!F11 -> 0 | C15: =BO!D60 -> 0 | D15: =B15-C15 -> 0
A16: Pagamento de Restos a Pagar Não processados do BF = Restos a Pagar Não Processados pagos do BO | B16: =BF!F26 -> 0 | C16: =BO!E75 -> 0 | D16: =B16-C16 -> 0
A17: Pagamento de Restos a Pagar processados do BF = Restos a Pagar Processados pagos do BO | B17: =BF!F27 -> 0 | C17: =BO!D88 -> 0 | D17: =B17-C17 -> 0
A18: Caixa final da BF (informado) = Caixa final do BF (calculado) | B18: =BF!F30 -> 0 | C18: =BF!B30+BF!B11+BF!B20+BF!B25-BF!F11-BF!F20-BF!F25 -> 0 | D18: =B18-C18 -> 0
A19: Total de ingressos do BF = Total de dispêndios do BF | B19: =BF!B34 -> 0 | C19: =BF!F34 -> 0 | D19: =B19-C19 -> 0
