Workbook

Sheet DCL TCERS
C1: Ano Anterior | D1: 1º semestre | E1: Bimestre Anterior | F1: Bimestre Atual
A2: Discriminação | B2: Codificação | C2: 42735 | D2: 42916 | E2: 42855 | F2: 42916 | G2: Mapeamento | H2: Valores
A3: (1) DÍVIDA CONSOLIDADA OU FUNDADA | C3: =SUM(C4:C62,C71:C138,C148:C166)-SUM(C63:C70,C139:C147) -> 0 | D3: =SUM(D4:D62,D71:D138,D148:D166)-SUM(D63:D70,D139:D147) -> 0 | E3: =SUM(E4:E62,E71:E138,E148:E166)-SUM(E63:E70,E139:E147) -> 0 | F3: =SUM(F4:F62,F71:F138,F148:F166)-SUM(F63:F70,F139:F147) -> 0 | G3: RGF | H3: =C2 -> 42735 | I3: =D2 -> 42916 | J3: 43100
A4: Precatórios de Pessoal – Regime Especial – a partir de 05/05/2000 – Vencidos e não pagos | B4: 2.1.1.1.1.04.02.00.00.00 | G4: precatorios | H4: =C4 -> 0 | I4: =D4 -> 0 | J4: =IF($F$2=$J$3,F4,0) -> 0
A5: Precatórios de Pessoal – Regime Ordinário – a partir de 05/05/2000 – Vencidos e não pagos | B5: 2.1.1.1.1.05.02.00.00.00 | G5: precatorios | H5: =C5 -> 0 | I5: =D5 -> 0 | J5: =IF($F$2=$J$3,F5,0) -> 0
A6: Precatórios de Benefícios Previdenciários – Regime Especial – a partir de 05/05/2000 – Vencidos e não pagos | B6: 2.1.1.2.1.04.02.00.00.00 | G6: precatorios | H6: =C6 -> 0 | I6: =D6 -> 0 | J6: =IF($F$2=$J$3,F6,0) -> 0
A7: Precatórios de Benefícios Previdenciários – Regime Ordinário – a partir de 05/05/2000 – Vencidos e não pagos | B7: 2.1.1.2.1.05.02.00.00.00 | G7: precatorios | H7: =C7 -> 0 | I7: =D7 -> 0 | J7: =IF($F$2=$J$3,F7,0) -> 0
A8: Precatórios de Benefícios Assistenciais – Regime Especial – a partir de 05/05/2000 – Vencidos e não pagos | B8: 2.1.1.3.1.03.02.00.00.00 | G8: precatorios | H8: =C8 -> 0 | I8: =D8 -> 0 | J8: =IF($F$2=$J$3,F8,0) -> 0
A9: Precatórios de Benefícios Assistenciais – Regime Ordinário – a partir de 05/05/2000 – Vencidos e não pagos | B9: 2.1.1.3.1.04.02.00.00.00 | G9: precatorios | H9: =C9 -> 0 | I9: =D9 -> 0 | J9: =IF($F$2=$J$3,F9,0) -> 0
A10: Contribuições ao RGPS – Débito Parcelado | B10: 2.1.1.4.1.01.02.00.00.00 | G10: parcelamento-previdenciario | H10: =C10 -> 0 | I10: =D10 -> 0 | J10: =IF($F$2=$J$3,F10,0) -> 0
A11: Contribuições ao RGPS – Débito Parcelado | B11: 2.1.1.4.3.01.02.00.00.00 | G11: parcelamento-previdenciario | H11: =C11 -> 0 | I11: =D11 -> 0 | J11: =IF($F$2=$J$3,F11,0) -> 0
A12: Contribuições Previdenciárias – Débito Parcelado | B12: 2.1.1.4.1.06.00.00.00.00 | G12: parcelamento-previdenciario | H12: =C12 -> 0 | I12: =D12 -> 0 | J12: =IF($F$2=$J$3,F12,0) -> 0
A13: Contribuições Previdenciárias – Débito Parcelado | B13: 2.1.1.4.3.06.00.00.00.00 | G13: parcelamento-previdenciario | H13: =C13 -> 0 | I13: =D13 -> 0 | J13: =IF($F$2=$J$3,F13,0) -> 0
A14: Contribuições Previdenciárias – Débito Parcelado | B14: 2.1.1.4.4.06.00.00.00.00 | G14: parcelamento-previdenciario | H14: =C14 -> 0 | I14: =D14 -> 0 | J14: =IF($F$2=$J$3,F14,0) -> 0
A15: Contribuições Previdenciárias – Débito Parcelado | B15: 2.1.1.4.5.06.00.00.00.00 | G15: parcelamento-previdenciario | H15: =C15 -> 0 | I15: =D15 -> 0 | J15: =IF($F$2=$J$3,F15,0) -> 0
... A62: Encargos – Financiamentos Externo | B62: 2.1.2.6.1.04.00.00.00.00 | G62: contratual-financiamento-externo | H62: =C62 -> 0 | I62: =D62 -> 0 | J62: =IF($F$2=$J$3,F62,0) -> 0
A63: (-) Encargos Financeiros a Apropriar – Empréstimo Interno | B63: 2.1.2.8.1.01.00.00.00.00 | G63: contratual-emprestimo-interno | H63: =C63*-1 -> 0 | I63: =D63*-1 -> 0 | J63: =IF($F$2=$J$3,F63,0)*-1 -> 0
A64: (-) Encargos Financeiros a Apropriar – Financiamento Interno | B64: 2.1.2.8.1.02.00.00.00.00 | G64: contratual-financiamento-interno | H64: =C64*-1 -> 0 | I64: =D64*-1 -> 0 | J64: =IF($F$2=$J$3,F64,0)*-1 -> 0
A65: (-) Encargos Financeiros a Apropriar – Empréstimo Interno | B65: 2.1.2.8.3.01.00.00.00.00 | G65: contratual-emprestimo-interno | H65: =C65*-1 -> 0 | I65: =D65*-1 -> 0 | J65: =IF($F$2=$J$3,F65,0)*-1 -> 0
A66: (-) Encargos Financeiros a Apropriar – Financiamento Interno | B66: 2.1.2.8.3.02.00.00.00.00 | G66: contratual-financiamento-interno | H66: =C66*-1 -> 0 | I66: =D66*-1 -> 0 | J66: =IF($F$2=$J$3,F66,0)*-1 -> 0
A67: (-) Encargos Financeiros a Apropriar – Empréstimo Interno | B67: 2.1.2.8.4.01.00.00.00.00 | G67: contratual-emprestimo-interno | H67: =C67*-1 -> 0 | I67: =D67*-1 -> 0 | J67: =IF($F$2=$J$3,F67,0)*-1 -> 0
A68: (-) Encargos Financeiros a Apropriar – Financiamento Interno | B68: 2.1.2.8.4.02.00.00.00.00 | G68: contratual-financiamento-interno | H68: =C68*-1 -> 0 | I68: =D68*-1 -> 0 | J68: =IF($F$2=$J$3,F68,0)*-1 -> 0
A69: (-) Encargos Financeiros a Apropriar – Consolidação – Interno – Empréstimo | B69: 2.1.2.9.1.01.00.00.00.00 | G69: contratual-emprestimo-interno | H69: =C69*-1 -> 0 | I69: =D69*-1 -> 0 | J69: =IF($F$2=$J$3,F69,0)*-1 -> 0
A70: (-) Encargos Financeiros a Apropriar – Consolidação – Interno – Financiamento | B70: 2.1.2.9.1.02.00.00.00.00 | G70: contratual-financiamento-interno | H70: =C70*-1 -> 0 | I70: =D70*-1 -> 0 | J70: =IF($F$2=$J$3,F70,0)*-1 -> 0
A71: Fornecedores Financiados a Pagar | B71: 2.1.3.1.1.01.02.00.00.00 | G71: outras-dividas | H71: =C71 -> 0 | I71: =D71 -> 0 | J71: =IF($F$2=$J$3,F71,0) -> 0
A72: Parcelamento de Fornecedores a Pagar | B72: 2.1.3.1.1.01.03.00.00.00 | G72: outras-dividas | H72: =C72 -> 0 | I72: =D72 -> 0 | J72: =IF($F$2=$J$3,F72,0) -> 0
A73: Contas Financiadas a Pagar | B73: 2.1.3.1.1.03.02.00.00.00 | G73: outras-dividas | H73: =C73 -> 0 | I73: =D73 -> 0 | J73: =IF($F$2=$J$3,F73,0) -> 0
A74: Parcelamento de Contas a Pagar | B74: 2.1.3.1.1.03.03.00.00.00 | G74: outras-dividas | H74: =C74 -> 0 | I74: =D74 -> 0 | J74: =IF($F$2=$J$3,F74,0) -> 0
A75: Precatórios de Fornecedores Nacionais – Regime Especial – a partir de 05/05/2000 – Vencidos e não pagos | B75: 2.1.3.1.1.05.02.00.00.00 | G75: precatorios | H75: =C75 -> 0 | I75: =D75 -> 0 | J75: =IF($F$2=$J$3,F75,0) -> 0
A76: Precatórios de Fornecedores Nacionais – Regime Ordinário – a partir de 05/05/2000 – Vencidos e não pagos | B76: 2.1.3.1.1.06.02.00.00.00 | G76: precatorios | H76: =C76 -> 0 | I76: =D76 -> 0 | J76: =IF($F$2=$J$3,F76,0) -> 0
A77: Precatórios de Contas a Pagar – Regime Especial – a partir de 05/05/2000 – Vencidos e não pagos | B77: 2.1.3.1.1.07.02.00.00.00 | G77: precatorios | H77: =C77 -> 0 | I77: =D77 -> 0 | J77: =IF($F$2=$J$3,F77,0) -> 0
A78: Precatórios de Contas a Pagar – Regime Ordinário – a partir de 05/05/2000 – Vencidos e não pagos | B78: 2.1.3.1.1.08.02.00.00.00 | G78: precatorios | H78: =C78 -> 0 | I78: =D78 -> 0 | J78: =IF($F$2=$J$3,F78,0) -> 0
A79: Fornecedores Financiados a Pagar | B79: 2.1.3.2.1.01.02.00.00.00 | G79: outras-dividas | H79: =C79 -> 0 | I79: =D79 -> 0 | J79: =IF($F$2=$J$3,F79,0) -> 0
A80: Parcelamento de Fornecedores a Pagar | B80: 2.1.3.2.1.01.03.00.00.00 | G80: outras-dividas | H80: =C80 -> 0 | I80: =D80 -> 0 | J80: =IF($F$2=$J$3,F80,0) -> 0
A81: Contas Financiadas a Pagar | B81: 2.1.3.2.1.02.02.00.00.00 | G81: outras-dividas | H81: =C81 -> 0 | I81: =D81 -> 0 | J81: =IF($F$2=$J$3,F81,0) -> 0
A82: Parcelamento de Contas a Pagar | B82: 2.1.3.2.1.02.03.00.00.00 | G82: outras-dividas | H82: =C82 -> 0 | I82: =D82 -> 0 | J82: =IF($F$2=$J$3,F82,0) -> 0
... A138: Encargos – Financiamentos Externo | B138: 2.2.2.6.1.04.00.00.00.00 | G138: contratual-financiamento-externo | H138: =C138 -> 0 | I138: =D138 -> 0 | J138: =IF($F$2=$J$3,F138,0) -> 0
A139: (-) Encargos Financeiros a Apropriar – Interno Empréstimo | B139: 2.2.2.8.1.01.00.00.00.00 | G139: contratual-emprestimo-interno | H139: =C139*-1 -> 0 | I139: =D139*-1 -> 0 | J139: =IF($F$2=$J$3,F139,0)*-1 -> 0
A140: (-) Encargos Financeiros a Apropriar – Interno Financiamento | B140: 2.2.2.8.1.02.00.00.00.00 | G140: contratual-financiamento-interno | H140: =C140*-1 -> 0 | I140: =D140*-1 -> 0 | J140: =IF($F$2=$J$3,F140,0)*-1 -> 0
A141: (-) Encargos Financeiros a Apropriar – Interno Empréstimo | B141: 2.2.2.8.3.01.00.00.00.00 | G141: contratual-emprestimo-interno | H141: =C141*-1 -> 0 | I141: =D141*-1 -> 0 | J141: =IF($F$2=$J$3,F141,0)*-1 -> 0
A142: (-) Encargos Financeiros a Apropriar – Interno Financiamento | B142: 2.2.2.8.3.02.00.00.00.00 | G142: contratual-financiamento-interno | H142: =C142*-1 -> 0 | I142: =D142*-1 -> 0 | J142: =IF($F$2=$J$3,F142,0)*-1 -> 0
A143: (-) Encargos Financeiros a Apropriar – Interno Empréstimo | B143: 2.2.2.8.4.01.00.00.00.00 | G143: contratual-emprestimo-interno | H143: =C143*-1 -> 0 | I143: =D143*-1 -> 0 | J143: =IF($F$2=$J$3,F143,0)*-1 -> 0
A144: (-) Encargos Financeiros a Apropriar – Interno Financiamento | B144: 2.2.2.8.4.02.00.00.00.00 | G144: contratual-financiamento-interno | H144: =C144*-1 -> 0 | I144: =D144*-1 -> 0 | J144: =IF($F$2=$J$3,F144,0)*-1 -> 0
A145: (-) Encargos Financeiros a Apropriar – Interno Empréstimo | B145: 2.2.2.8.5.01.00.00.00.00 | G145: contratual-emprestimo-interno | H145: =C145*-1 -> 0 | I145: =D145*-1 -> 0 | J145: =IF($F$2=$J$3,F145,0)*-1 -> 0
A146: (-) Encargos Financeiros a Apropriar – Interno Financiamento | B146: 2.2.2.8.5.02.00.00.00.00 | G146: contratual-financiamento-interno | H146: =C146*-1 -> 0 | I146: =D146*-1 -> 0 | J146: =IF($F$2=$J$3,F146,0)*-1 -> 0
A147: (-) Encargos Prefixados de Empréstimos Externos | B147: 2.2.2.9.1.01.00.00.00.00 | G147: contratual-emprestimo-externo | H147: =C147*-1 -> 0 | I147: =D147*-1 -> 0 | J147: =IF($F$2=$J$3,F147,0)*-1 -> 0
A148: Fornecedores Financiados a Pagar | B148: 2.2.3.1.1.01.02.00.00.00 | G148: contratual-demais | H148: =C148 -> 0 | I148: =D148 -> 0 | J148: =IF($F$2=$J$3,F148,0) -> 0
A149: Parcelamento de Fornecedores a Pagar | B149: 2.2.3.1.1.01.03.00.00.00 | G149: contratual-demais | H149: =C149 -> 0 | I149: =D149 -> 0 | J149: =IF($F$2=$J$3,F149,0) -> 0
A150: Precatórios de Fornecedores Nacionais – Regime Especial – a partir de 05/05/2000 – Vencidos e não pagos | B150: 2.2.3.1.1.04.02.00.00.00 | G150: precatorios | H150: =C150 -> 0 | I150: =D150 -> 0 | J150: =IF($F$2=$J$3,F150,0) -> 0
A151: Precatórios de Fornecedores Nacionais – Regime Ordinário – a partir de 05/05/2000 – Vencidos e não pagos | B151: 2.2.3.1.1.05.02.00.00.00 | G151: precatorios | H151: =C151 -> 0 | I151: =D151 -> 0 | J151: =IF($F$2=$J$3,F151,0) -> 0
A152: Precatórios de Contas a Pagar – Regime Especial – a partir de 05/05/2000 – Vencidos e não pagos | B152: 2.2.3.1.1.06.02.00.00.00 | G152: precatorios | H152: =C152 -> 0 | I152: =D152 -> 0 | J152: =IF($F$2=$J$3,F152,0) -> 0
A153: Precatórios de Contas a Pagar – Regime Ordinário – a partir de 05/05/2000 – Vencidos e não pagos | B153: 2.2.3.1.1.07.02.00.00.00 | G153: precatorios | H153: =C153 -> 0 | I153: =D153 -> 0 | J153: =IF($F$2=$J$3,F153,0) -> 0
A154: Fornecedores Financiados a Pagar | B154: 2.2.3.2.1.01.02.00.00.00 | G154: contratual-demais | H154: =C154 -> 0 | I154: =D154 -> 0 | J154: =IF($F$2=$J$3,F154,0) -> 0
A155: Parcelamento de Fornecedores a Pagar | B155: 2.2.3.2.1.01.03.00.00.00 | G155: contratual-demais | H155: =C155 -> 0 | I155: =D155 -> 0 | J155: =IF($F$2=$J$3,F155,0) -> 0
A156: Tributos Federais Renegociados | B156: 2.2.4.1.1.02.00.00.00.00 | G156: parcelamento-tributos | H156: =C156 -> 0 | I156: =D156 -> 0 | J156: =IF($F$2=$J$3,F156,0) -> 0
A157: Tributos Federais Renegociados | B157: 2.2.4.1.2.02.00.00.00.00 | G157: parcelamento-tributos | H157: =C157 -> 0 | I157: =D157 -> 0 | J157: =IF($F$2=$J$3,F157,0) -> 0
A158: Tributos Federais Renegociados | B158: 2.2.4.1.3.02.00.00.00.00 | G158: parcelamento-tributos | H158: =C158 -> 0 | I158: =D158 -> 0 | J158: =IF($F$2=$J$3,F158,0) -> 0
A159: Tributos Estaduais Renegociados | B159: 2.2.4.2.1.01.00.00.00.00 | G159: parcelamento-tributos | H159: =C159 -> 0 | I159: =D159 -> 0 | J159: =IF($F$2=$J$3,F159,0) -> 0
... A166: Operação de Crédito Contratada pelo Consórcio Público | B166: 8.5.3.6.0.00.00.00.00.00 | G166: outras-dividas | H166: =C166 -> 0 | I166: =D166 -> 0 | J166: =IF($F$2=$J$3,F166,0) -> 0
A168: (2) DEDUÇÕES | C168: =IF(C170<C177,C180,C170-C177+C180) -> 2834903.8 | D168: =IF(D170<D177,D180,D170-D177+D180) -> 3799039.9 | E168: =IF(E170<E177,E180,E170-E177+E180) -> 3824678.1 | F168: =IF(F170<F177,F180,F170-F177+F180) -> 3799039.9
A170: (3) DISPONIBILIDADE DE CAIXA BRUTA | C170: =SUM(C171:C175) -> 2861963.9 | D170: =SUM(D171:D175) -> 3814559.9 | E170: =SUM(E171:E175) -> 3840198.1 | F170: =SUM(F171:F175) -> 3814559.9 | H170: =C170 -> 2861963.9 | I170: =D170 -> 3814559.9 | J170: =IF($F$2=$J$3,F170,0) -> 0
A171: Conta Única | B171: 1.1.1.1.1.02.00.00.00.00 | G171: caixa
A172: Bancos Conta Movimento – Demais Contas | B172: 1.1.1.1.1.19.00.00.00.00 | C172: 452979.04 | D172: 44671.63 | E172: 83455.61 | F172: 44671.63 | G172: caixa
A173: Rede Bancária – Arrecadação | B173: 1.1.1.1.1.30.00.00.00.00 | G173: caixa
A174: Aplicações Financeiras de Liquidez Imediata | B174: 1.1.1.1.1.50.00.00.00.00 | C174: 2408984.9 | D174: 3769888.3 | E174: 3756742.5 | F174: 3769888.3 | G174: caixa
A175: Caixa e Equivalente de Caixa em Moeda Estrangeira – Consolidação | B175: 1.1.1.2.1.00.00.00.00.00 | G175: caixa
A177: (4) RESTOS A PAGAR PROCESSADOS | C177: =SUM(C178) -> 27060.09 | D177: =SUM(D178) -> 15520.04 | E177: =SUM(E178) -> 15520.04 | F177: =SUM(F178) -> 15520.04 | H177: =C177 -> 27060.09 | I177: =D177 -> 15520.04 | J177: =IF($F$2=$J$3,F177,0) -> 0
A178: Restos a Pagar Processados | B178: 6.3.2.1.0.00.00.00.00.00 | C178: 27060.09 | D178: 15520.04 | E178: 15520.04 | F178: 15520.04 | G178: processados
A180: (5) DEMAIS HAVERES FINANCEIROS | C180: =SUM(C181:C192,C198:C204,C206:C207,C209,C213:C221)-SUM(C193:C197,C205,C208,C210:C212) -> 0 | D180: =SUM(D181:D192,D198:D204,D206:D207,D209,D213:D221)-SUM(D193:D197,D205,D208,D210:D212) -> 0 | E180: =SUM(E181:E192,E198:E204,E206:E207,E209,E213:E221)-SUM(E193:E197,E205,E208,E210:E212) -> 0 | F180: =SUM(F181:F192,F198:F204,F206:F207,F209,F213:F221)-SUM(F193:F197,F205,F208,F210:F212) -> 0 | H180: =C180 -> 0 | I180: =D180 -> 0 | J180: =IF($F$2=$J$3,F180,0) -> 0
A181: Empréstimos Concedidos | B181: 1.1.2.4.1.01.00.00.00.00 | G181: haveres
A182: Empréstimos Concedidos | B182: 1.1.2.4.3.01.00.00.00.00 | G182: haveres
A183: Empréstimos Concedidos | B183: 1.1.2.4.4.01.00.00.00.00 | G183: haveres
A184: Empréstimos Concedidos | B184: 1.1.2.4.5.01.00.00.00.00 | G184: haveres
A185: Financiamentos Concedidos | B185: 1.1.2.4.1.02.00.00.00.00 | G185: haveres
A186: Financiamentos Concedidos | B186: 1.1.2.4.3.02.00.00.00.00 | G186: haveres
A187: Financiamentos Concedidos | B187: 1.1.2.4.4.02.00.00.00.00 | G187: haveres
A188: Financiamentos Concedidos | B188: 1.1.2.4.5.02.00.00.00.00 | G188: haveres
A189: Juros e Encargos sobre Empréstimos e Financiamentos Concedidos a Receber | B189: 1.1.2.4.1.03.00.00.00.00 | G189: haveres
A190: Juros e Encargos sobre Empréstimos e Financiamentos Concedidos a Receber | B190: 1.1.2.4.3.03.00.00.00.00 | G190: haveres
A191: Juros e Encargos sobre Empréstimos e Financiamentos Concedidos a Receber | B191: 1.1.2.4.4.03.00.00.00.00 | G191: haveres
A192: Juros e Encargos sobre Empréstimos e Financiamentos Concedidos a Receber | B192: 1.1.2.4.5.03.00.00.00.00 | G192: haveres
... A221: Investimentos e Aplicações Temporárias a Longo Prazo – Consolidação | B221: 1.2.1.3.1.00.00.00.00.00 | G221: haveres
A223: (6) DÍVIDA CONSOLIDADA LÍQUIDA | C223: =C3-C168 -> -2834903.8 | D223: =D3-D168 -> -3799039.9 | E223: =E3-E168 -> -3824678.1 | F223: =F3-F168 -> -3799039.9 | H223: =C223 -> -2834903.8 | I223: =D223 -> -3799039.9 | J223: =IF($F$2=$J$3,F223,0) -> 0
A225: (7) OUTRAS OBRIGAÇÕES NÃO INTEGRANTES DA DÍVIDA CONSOLIDADA LÍQUIDA | C225: =SUM(C226:C277) -> 708490.71 | D225: =SUM(D226:D277) -> 556768.21 | E225: =SUM(E226:E277) -> 562015.67 | F225: =SUM(F226:F277) -> 556768.21 | H225: =C225 -> 708490.71 | I225: =D225 -> 556768.21 | J225: =IF($F$2=$J$3,F225,0) -> 0
A226: Precatórios de Pessoal – Regime Especial – antes de 05/05/2000 | B226: 2.1.1.1.1.04.01.00.00.00 | G226: precatorios-antes
A227: Precatórios de Pessoal – Regime Especial – a partir de 05/05/2000 – Não Vencidos | B227: 2.1.1.1.1.04.03.00.00.00 | G227: precatorios
A228: Precatórios de Pessoal – Regime Ordinário – antes de 05/05/2000 | B228: 2.1.1.1.1.05.01.00.00.00 | G228: precatorios-antes
A229: Precatórios de Pessoal – Regime Ordinário – a partir de 05/05/2000 – Não Vencidos | B229: 2.1.1.1.1.05.03.00.00.00 | G229: precatorios
A230: Precatórios de Benefícios Previdenciários – Regime Especial – antes de 05/05/2000 | B230: 2.1.1.2.1.04.01.00.00.00 | G230: precatorios-antes
A231: Precatórios de Benefícios Previdenciários – Regime Especial – a partir de 05/05/2000 – Não Vencidos | B231: 2.1.1.2.1.04.03.00.00.00 | G231: precatorios
A232: Precatórios de Benefícios Previdenciários – Regime Ordinário – antes de 05/05/2000 | B232: 2.1.1.2.1.05.01.00.00.00 | G232: precatorios-antes
A233: Precatórios de Benefícios Previdenciários – Regime Ordinário – a partir de 05/05/2000 – Não Vencidos | B233: 2.1.1.2.1.05.03.00.00.00 | G233: precatorios
A234: Precatórios de Benefícios Assistenciais – Regime Especial – antes de 05/05/2000 | B234: 2.1.1.3.1.03.01.00.00.00 | G234: precatorios-antes
A235: Precatórios de Benefícios Assistenciais – Regime Especial – a partir de 05/05/2000 – Não Vencidos | B235: 2.1.1.3.1.03.03.00.00.00 | G235: precatorios
A236: Precatórios de Benefícios Assistenciais – Regime Ordinário – antes de 05/05/2000 | B236: 2.1.1.3.1.04.01.00.00.00 | G236: precatorios-antes
A237: Precatórios de Benefícios Assistenciais – Regime Ordinário – a partir de 05/05/2000 – Não Vencidos | B237: 2.1.1.3.1.04.03.00.00.00 | G237: precatorios
... A249: Precatórios de Contas a Pagar – Regime Ordinário – a partir de 05/05/2000 – Não Vencidos | B249: 2.1.3.1.1.08.03.00.00.00 | G249: precatorios
A250: Valores Restituíveis | B250: 2.1.8.8.0.00.00.00.00.00 | D250: 214046.02 | E250: 74620.32 | F250: 214046.02 | G250: depositos
A251: Precatórios de Pessoal – Regime Especial – antes de 05/05/2000 | B251: 2.2.1.1.1.03.01.00.00.00 | G251: precatorios-antes
A252: Precatórios de Pessoal – Regime Especial – a partir de 05/05/2000 – Não Vencidos | B252: 2.2.1.1.1.03.03.00.00.00 | G252: precatorios
...

Sheet RREO Anexo 5 - Resultado Nominal
A1: MUNICÍPIO DE INDEPENDÊNCIA – RS
A2: RELATÓRIO RESUMIDO DA EXECUÇÃO ORÇAMENTÁRIA
A3: DEMONSTRATIVO DO RESULTADO NOMINAL
A4: ORÇAMENTOS FISCAL E DA SEGURIDADE SOCIAL
A5: =CONCATENATE(MONTH('DCL TCERS'!F2)/2,"º Bimestre de ",YEAR('DCL TCERS'!F2)) -> 3º Bimestre de 2017
A7: RREO - ANEXO 5 (LRF, art 53, inciso III) | G7: Em Reais
D8: SALDO
A9: DÍVIDA FISCAL LÍQUIDA | B9: =CONCATENATE("Em ",DAY('DCL TCERS'!C2),"/",MONTH('DCL TCERS'!C2),"/",YEAR('DCL TCERS'!C2)) -> Em 31/12/2016 | D9: =CONCATENATE("Em ",DAY('DCL TCERS'!E2),"/",MONTH('DCL TCERS'!E2),"/",YEAR('DCL TCERS'!E2)) -> Em 30/4/2017 | F9: =CONCATENATE("Em ",DAY('DCL TCERS'!F2),"/",MONTH('DCL TCERS'!F2),"/",YEAR('DCL TCERS'!F2)) -> Em 30/6/2017
B10: (a) | D10: (b) | F10: (c)
A11: DÍVIDA CONSOLIDADA (I) | B11: ='DCL TCERS'!C3 -> 0 | D11: ='DCL TCERS'!E3 -> 0 | F11: ='DCL TCERS'!F3 -> 0
A12: DEDUÇÕES (II) | B12: ='DCL TCERS'!C168 -> 2834903.8 | D12: ='DCL TCERS'!E168 -> 3824678.1 | F12: ='DCL TCERS'!F168 -> 3799039.9
A13: Disponibilidade de Caixa | B13: =IF(B14<B15,0,B14-B15) -> 2834903.8 | D13: =IF(E14<E15,0,E14-E15) -> 0 | F13: =IF(F14<F15,0,F14-F15) -> 3799039.9
A14: Disponibilidade de Caixa Bruta | B14: ='DCL TCERS'!C170 -> 2861963.9 | D14: ='DCL TCERS'!E170 -> 3840198.1 | F14: ='DCL TCERS'!F170 -> 3814559.9
A15: (-) Restos a Pagar Processados (Exceto precatórios) | B15: ='DCL TCERS'!C177 -> 27060.09 | D15: ='DCL TCERS'!E177 -> 15520.04 | F15: ='DCL TCERS'!F177 -> 15520.04
A16: Demais Haveres Financeiros | B16: ='DCL TCERS'!C180 -> 0 | D16: ='DCL TCERS'!E180 -> 0 | F16: ='DCL TCERS'!F180 -> 0
A17: DÍVIDA CONSOLIDADA LÍQUIDA (III) = (I - II) | B17: =B11-B12 -> -2834903.8 | D17: =D11-D12 -> -3824678.1 | F17: =F11-F12 -> -3799039.9
A18: RECEITA DE PRIVATIZAÇÕES (IV)
A19: PASSIVOS RECONHECIDOS (V)
A20: DÍVIDA FISCAL LÍQUIDA (VI) = (III + IV - V) | B20: =B17+B18-B19 -> -2834903.8 | D20: =D17+D18-D19 -> -3824678.1 | F20: =F17+F18-F19 -> -3799039.9
B22: PERÍODO DE REFERÊNCIA
A23: RESULTADO NOMINAL | B23: No Bimestre | E23: Até o Bimestre
B24: (VIc -VIb) | E24: (VIc - VIa)
A25: VALOR | B25: =F20-D20 -> 25638.19 | E25: =F20-B20 -> -964136.08
A27: DISCRIMINAÇÃO DA META FISCAL | E27: VALOR CORRENTE
A29: META DE RESULTADO NOMINAL FIXADA NO ANEXO DE METAS FISCAIS DA LDO P/ O EXERCÍCIO DE REFERÊNCIA | E29: 0

Sheet RGF Anexo 2 - DCL
A1: ='RREO Anexo 5 - Resultado Nominal'!A1 -> MUNICÍPIO DE INDEPENDÊNCIA – RS
A2: RELATÓRIO DE GESTÃO FISCAL
A3: DEMONSTRATIVO DA DÍVIDA CONSOLIDADA LÍQUIDA
A4: ORÇAMENTOS FISCAL E DA SEGURIDADE SOCIAL
A5: =CONCATENATE(IF(MONTH('DCL TCERS'!F2)=4,"1º quadrimestre de ",IF(MONTH('DCL TCERS'!F2)=6,"1º semestre de ",IF(MONTH('DCL TCERS'!F2)=8,"2º quadrimestre de ","2º semestre/3º quadrimestre de "))),YEAR('DCL TCERS'!F2)) -> 1º semestre de 2017
A7: RGF - ANEXO 2 (LRF, art. 55, inciso I, alínea "b") | D7: 1
A8: DÍVIDA CONSOLIDADA | B8: SALDO DO | C8: =CONCATENATE("SALDO DO EXERCÍCIO DE ",YEAR('DCL TCERS'!F2)) -> SALDO DO EXERCÍCIO DE 2017
B9: EXERCÍCIO ANTERIOR | C9: Até o 1º Semestre | D9: Até o 2º Semestre
A10: DÍVIDA CONSOLIDADA - DC (I) | B10: =B11+B12+B27+B28 -> 0 | C10: =C11+C12+C27+C28 -> 0 | D10: =D11+D12+D27+D28 -> 0
A11: Dívida Mobiliária | B11: =SUMIF('DCL TCERS'!$G$4:$G$166,"mobiliaria",'DCL TCERS'!H4:H166) -> 0 | C11: =SUMIF('DCL TCERS'!$G$4:$G$166,"mobiliaria",'DCL TCERS'!I4:I166) -> 0 | D11: =SUMIF('DCL TCERS'!$G$4:$G$166,"mobiliaria",'DCL TCERS'!J4:J166) -> 0
A12: Dívida Contratual | B12: =B13+B16+B17+B20+B26 -> 0 | C12: =C13+C16+C17+C20+C26 -> 0 | D12: =D13+D16+D17+D20+D26 -> 0
A13: Empréstimos | B13: =SUM(B14:B15) -> 0 | C13: =SUM(C14:C15) -> 0 | D13: =SUM(D14:D15) -> 0
A14: Internos | B14: =SUMIF('DCL TCERS'!$G$4:$G$166,"contratual-emprestimo-interno",'DCL TCERS'!H4:H166) -> 0 | C14: =SUMIF('DCL TCERS'!$G$4:$G$166,"contratual-emprestimo-interno",'DCL TCERS'!I4:I166) -> 0 | D14: =SUMIF('DCL TCERS'!$G$4:$G$166,"contratual-emprestimo-interno",'DCL TCERS'!J4:J166) -> 0
A15: Externos | B15: =SUMIF('DCL TCERS'!$G$4:$G$166,"contratual-emprestimo-externo",'DCL TCERS'!H4:H166) -> 0 | C15: =SUMIF('DCL TCERS'!$G$4:$G$166,"contratual-emprestimo-externo",'DCL TCERS'!I4:I166) -> 0 | D15: =SUMIF('DCL TCERS'!$G$4:$G$166,"contratual-emprestimo-externo",'DCL TCERS'!J4:J166) -> 0
A16: Reestruturação da Dívida de Estados e Municípios | B16: =SUMIF('DCL TCERS'!$G$4:$G$166,"reestruturacao",'DCL TCERS'!H4:H166) -> 0 | C16: =SUMIF('DCL TCERS'!$G$4:$G$166,"reestruturacao",'DCL TCERS'!I4:I166) -> 0 | D16: =SUMIF('DCL TCERS'!$G$4:$G$166,"reestruturacao",'DCL TCERS'!J4:J166) -> 0
A17: Financiamentos | B17: =SUM(B18:B19) -> 0 | C17: =SUM(C18:C19) -> 0 | D17: =SUM(D18:D19) -> 0
A18: Internos | B18: =SUMIF('DCL TCERS'!$G$4:$G$166,"contratual-financiamento-interno",'DCL TCERS'!H4:H166) -> 0 | C18: =SUMIF('DCL TCERS'!$G$4:$G$166,"contratual-financiamento-interno",'DCL TCERS'!I4:I166) -> 0 | D18: =SUMIF('DCL TCERS'!$G$4:$G$166,"contratual-financiamento-interno",'DCL TCERS'!J4:J166) -> 0
A19: Externos | B19: =SUMIF('DCL TCERS'!$G$4:$G$166,"contratual-financiamento-externo",'DCL TCERS'!H4:H166) -> 0 | C19: =SUMIF('DCL TCERS'!$G$4:$G$166,"contratual-financiamento-externo",'DCL TCERS'!I4:I166) -> 0 | D19: =SUMIF('DCL TCERS'!$G$4:$G$166,"contratual-financiamento-externo",'DCL TCERS'!J4:J166) -> 0
A20: Parcelamento e Renegociação de dívidas | B20: =SUM(B21:B25) -> 0 | C20: =SUM(C21:C25) -> 0 | D20: =SUM(D21:D25) -> 0
A21: De Tributos | B21: =SUMIF('DCL TCERS'!$G$4:$G$166,"parcelamento-tributos",'DCL TCERS'!H4:H166) -> 0 | C21: =SUMIF('DCL TCERS'!$G$4:$G$166,"parcelamento-tributos",'DCL TCERS'!I4:I166) -> 0 | D21: =SUMIF('DCL TCERS'!$G$4:$G$166,"parcelamento-tributos",'DCL TCERS'!J4:J166) -> 0
A22: De Contribuições Previdenciárias | B22: =SUMIF('DCL TCERS'!$G$4:$G$166,"parcelamento-previdenciario",'DCL TCERS'!H4:H166) -> 0 | C22: =SUMIF('DCL TCERS'!$G$4:$G$166,"parcelamento-previdenciario",'DCL TCERS'!I4:I166) -> 0 | D22: =SUMIF('DCL TCERS'!$G$4:$G$166,"parcelamento-previdenciario",'DCL TCERS'!J4:J166) -> 0
A23: De Demais Contribuições Sociais | B23: =SUMIF('DCL TCERS'!$G$4:$G$166,"parcelamento-contribuicao-social",'DCL TCERS'!H4:H166) -> 0 | C23: =SUMIF('DCL TCERS'!$G$4:$G$166,"parcelamento-contribuicao-social",'DCL TCERS'!I4:I166) -> 0 | D23: =SUMIF('DCL TCERS'!$G$4:$G$166,"parcelamento-contribuicao-social",'DCL TCERS'!J4:J166) -> 0
A24: Do FGTS | B24: =SUMIF('DCL TCERS'!$G$4:$G$166,"parcelamento-fgts",'DCL TCERS'!H4:H166) -> 0 | C24: =SUMIF('DCL TCERS'!$G$4:$G$166,"parcelamento-fgts",'DCL TCERS'!I4:I166) -> 0 | D24: =SUMIF('DCL TCERS'!$G$4:$G$166,"parcelamento-fgts",'DCL TCERS'!J4:J166) -> 0
A25: Com Instituição Não financeira
A26: Demais Dívidas Contratuais | B26: =SUMIF('DCL TCERS'!$G$4:$G$166,"contratual-demais",'DCL TCERS'!H4:H166) -> 0 | C26: =SUMIF('DCL TCERS'!$G$4:$G$166,"contratual-demais",'DCL TCERS'!I4:I166) -> 0 | D26: =SUMIF('DCL TCERS'!$G$4:$G$166,"contratual-demais",'DCL TCERS'!J4:J166) -> 0
A27: Precatórios Posteriores a 05/05/2000 (inclusive) - Vencidos e não pagos | B27: =SUMIF('DCL TCERS'!$G$4:$G$166,"precatorios",'DCL TCERS'!H4:H166) -> 0 | C27: =SUMIF('DCL TCERS'!$G$4:$G$166,"precatorios",'DCL TCERS'!I4:I166) -> 0 | D27: =SUMIF('DCL TCERS'!$G$4:$G$166,"precatorios",'DCL TCERS'!J4:J166) -> 0
A28: Outras Dívidas | B28: =SUMIF('DCL TCERS'!$G$4:$G$166,"outras-dividas",'DCL TCERS'!H4:H166) -> 0 | C28: =SUMIF('DCL TCERS'!$G$4:$G$166,"outras-dividas",'DCL TCERS'!I4:I166) -> 0 | D28: =SUMIF('DCL TCERS'!$G$4:$G$166,"outras-dividas",'DCL TCERS'!J4:J166) -> 0
A29: DEDUÇÕES (II) | B29: =B30+B33 -> 2834903.8 | C29: =C30+C33 -> 3799039.9 | D29: =D30+D33 -> 0
A30: Disponibilidade de Caixa¹ | B30: =IF(B31<B32,0,B31-B32) -> 2834903.8 | C30: =IF(C31<C32,0,C31-C32) -> 3799039.9 | D30: =IF(D31<D32,0,D31-D32) -> 0
A31: Disponibilidade de Caixa Bruta | B31: ='DCL TCERS'!H170 -> 2861963.9 | C31: ='DCL TCERS'!I170 -> 3814559.9 | D31: ='DCL TCERS'!J170 -> 0
A32: (-) Restos a Pagar Processados | B32: ='DCL TCERS'!H177 -> 27060.09 | C32: ='DCL TCERS'!I177 -> 15520.04 | D32: ='DCL TCERS'!J177 -> 0
A33: Demais Haveres Financeiros | B33: ='DCL TCERS'!H180 -> 0 | C33: ='DCL TCERS'!I180 -> 0 | D33: ='DCL TCERS'!J180 -> 0
A34: DÍVIDA CONSOLIDADA LÍQUIDA² (DCL) (III) = (I - II) | B34: =B10-B29 -> -2834903.8 | C34: =C10-C29 -> -3799039.9 | D34: =D10-D29 -> 0
A35: RECEITA CORRENTE LÍQUIDA - RCL | B35: 20601298 | C35: 20769803 | D35: 20690244
A36: % da DC sobre a RCL (I/RCL) | B36: =B10/B35 -> 0 | C36: =C10/C35 -> 0 | D36: =D10/D35 -> 0
A37: % da DCL sobre a RCL (III/RCL) | B37: =B34/B35 -> -0.13760802 | C37: =C34/C35 -> -0.18291169 | D37: =D34/D35 -> 0
A38: LIMITE DEFINIDO POR RESOLUÇÃO DO SENADO FEDERAL – 120% | B38: =B35*1.2 -> 24721558 | C38: =C35*1.2 -> 24923764 | D38: =D35*1.2 -> 24828293
A39: LIMITE DE ALERTA (inciso III do § 1º do art. 59 da LRF) – 108% | B39: =B35*1.08 -> 22249402 | C39: =C35*1.08 -> 22431387 | D39: =D35*1.08 -> 22345464
A41: OUTROS VALORES NÃO INTEGRANTES DA DC | B41: SALDO DO | C41: =CONCATENATE("SALDO DO EXERCÍCIO DE ",YEAR('DCL TCERS'!F2)) -> SALDO DO EXERCÍCIO DE 2017
B42: EXERCÍCIO ANTERIOR | C42: Até o 1º Semestre | D42: Até o 2º Semestre
A43: PRECATÓRIOS ANTERIORES A 05/05/2000 | B43: =SUMIF('DCL TCERS'!$G$226:$G$276,"precatorios-antes",'DCL TCERS'!C226:C276) -> 0 | C43: =SUMIF('DCL TCERS'!$G$226:$G$276,"precatorios-antes",'DCL TCERS'!D226:D276) -> 0 | D43: =SUMIF('DCL TCERS'!$G$226:$G$276,"precatorios-antes",'DCL TCERS'!F226:F276) -> 0
A44: PRECATÓRIOS POSTERIORES A 05/05/2000 (Não incluídos na DC)2 | B44: =SUMIF('DCL TCERS'!$G$226:$G$276,"precatorios",'DCL TCERS'!C226:C276) -> 0 | C44: =SUMIF('DCL TCERS'!$G$226:$G$276,"precatorios",'DCL TCERS'!D226:D276) -> 0 | D44: =SUMIF('DCL TCERS'!$G$226:$G$276,"precatorios",'DCL TCERS'!F226:F276) -> 0
A45: PASSIVO ATUARIAL | B45: =SUMIF('DCL TCERS'!$G$226:$G$276,"provisao",'DCL TCERS'!C226:C276) -> 0 | C45: =SUMIF('DCL TCERS'!$G$226:$G$276,"provisao",'DCL TCERS'!D226:D276) -> 0 | D45: =SUMIF('DCL TCERS'!$G$226:$G$276,"provisao",'DCL TCERS'!F226:F276) -> 0
A46: INSUFICIÊNCIA FINANCEIRA | B46: ='DCL TCERS'!C277 -> 0 | C46: ='DCL TCERS'!D277 -> 0 | D46: ='DCL TCERS'!F277 -> 0
A47: DEPÓSITOS | B47: =SUMIF('DCL TCERS'!$G$226:$G$276,"depositos",'DCL TCERS'!C226:C276) -> 0 | C47: =SUMIF('DCL TCERS'!$G$226:$G$276,"depositos",'DCL TCERS'!D226:D276) -> 214046.02 | D47: =SUMIF('DCL TCERS'!$G$226:$G$276,"depositos",'DCL TCERS'!F226:F276) -> 214046.02
A48: RP NÃO-PROCESSADOS | B48: =SUMIF('DCL TCERS'!$G$226:$G$276,"restos",'DCL TCERS'!C226:C276) -> 708490.71 | C48: =SUMIF('DCL TCERS'!$G$226:$G$276,"restos",'DCL TCERS'!D226:D276) -> 342722.19 | D48: =SUMIF('DCL TCERS'!$G$226:$G$276,"restos",'DCL TCERS'!F226:F276) -> 342722.19
A49: ANTECIPAÇÕES DE RECEITA ORÇAMENTÁRIA – ARO | B49: =SUMIF('DCL TCERS'!$G$226:$G$276,"aro",'DCL TCERS'!C226:C276) -> 0 | C49: =SUMIF('DCL TCERS'!$G$226:$G$276,"aro",'DCL TCERS'!D226:D276) -> 0 | D49: =SUMIF('DCL TCERS'!$G$226:$G$276,"aro",'DCL TCERS'!F226:F276) -> 0
A51: 1. Se o saldo apurado for negativo, ou seja, se o total da Disponibilidade de Caixa Bruta for menor que Restos a Pagar Processados, esse saldo negativo não deverá ser informado nessa linha, mas sim na linha da “Insuficiência Financeira”, no quadro "Outros Valores não integrantes da Dívida Consolidada". Assim, quando o cálculo de Disponibilidade de Caixa for negativo, o valor dessa linha deverá ser (0) "zero".
A52: 2. Refere-se aos precatórios posteriores a 05/05/2000 que, em cumprimento ao disposto no artigo 100 da Constituição Federal, ainda não foram incluídos no orçamento ou constam no orçamento e ainda não foram pagos. Ao final do exercício em que esses precatórios foram incluídos ou que deveriam ter sido incluídos, os valores deverão compor a linha "Precatórios Posteriores a 05/05/2000 (inclusive) - Vencidos e não pagos"
