Workbook

Sheet BO-REC
A1: BALANÇO ORÇAMENTÁRIO
A2: EXERCÍCIO DE 2015 | B2: DE 01/01/2015 A 31/12/2015
A3: RECEITAS ORÇAMENTÁRIAS | B3: PREVISÃO INICIAL | C3: PREVISÃO ATUALIZADA (a) | D3: RECEITAS REALIZADAS (b) | E3: SALDO (c = b-a)
A4: RECETAS CORRENTES | B4: =B5+B9+B13+B21+B25+B30+B31+B38 -> 0 | C4: =C5+C9+C13+C21+C25+C30+C31+C38 -> 0 | D4: =D5+D9+D13+D21+D25+D30+D31+D38 -> 0 | E4: =D4-C4 -> 0
A5: RECEITA TRIBUTÁRIA | B5: =SUM(B6:B8) -> 0 | C5: =SUM(C6:C8) -> 0 | D5: =SUM(D6:D8) -> 0 | E5: =D5-C5 -> 0
A6: Impostos | E6: =D6-C6 -> 0
A7: Taxas | E7: =D7-C7 -> 0
A8: Contribuição de melhoria | E8: =D8-C8 -> 0
A9: RECEITA DE CONTRIBUIÇÕES | B9: =SUM(B10:B12) -> 0 | C9: =SUM(C10:C12) -> 0 | D9: =SUM(D10:D12) -> 0 | E9: =D9-C9 -> 0
A10: Contribuição social | E10: =D10-C10 -> 0
A11: Contribuição de intervenção no domínio econômico | E11: =D11-C11 -> 0
A12: Contribuição de iluminação pública | E12: =D12-C12 -> 0
A13: RECEITA PATRIMONIAL | B13: =SUM(B14:B20) -> 0 | C13: =SUM(C14:C20) -> 0 | D13: =SUM(D14:D20) -> 0 | E13: =D13-C13 -> 0
A14: Receitas imobiliárias | E14: =D14-C14 -> 0
A15: Receitas de valores mobiliários | E15: =D15-C15 -> 0
A16: Receitas de concessões e permissões | E16: =D16-C16 -> 0
A17: Compensações financeiras | E17: =D17-C17 -> 0
A18: Receita decorrente do direito de exploração de bens públicos em áreas de domínio público | E18: =D18-C18 -> 0
A19: Receita de cessão de direitos | E19: =D19-C19 -> 0
A20: Outras receitas patrimoniais | E20: =D20-C20 -> 0
A21: RECEITA AGROPECUÁRIA | B21: =SUM(B22:B24) -> 0 | C21: =SUM(C22:C24) -> 0 | D21: =SUM(D22:D24) -> 0 | E21: =D21-C21 -> 0
A22: Receita da produção vegetal | E22: =D22-C22 -> 0
A23: Receita da produção animal e derivados | E23: =D23-C23 -> 0
A24: Outras receitas agropecuárias | E24: =D24-C24 -> 0
A25: RECEITA INDUSTRIAL | B25: =SUM(B26:B29) -> 0 | C25: =SUM(C26:C29) -> 0 | D25: =SUM(D26:D29) -> 0 | E25: =D25-C25 -> 0
A26: Receita da indústria extrativa mineral | E26: =D26-C26 -> 0
A27: Receita da indústria de transformação | E27: =D27-C27 -> 0
A28: Receita da indústria de construção | E28: =D28-C28 -> 0
A29: Outras receitas industriais | E29: =D29-C29 -> 0
A30: RECEITA DE SERVIÇOS | E30: =D30-C30 -> 0
A31: TRANSFERÊNCIAS CORRENTES | B31: =SUM(B32:B37) -> 0 | C31: =SUM(C32:C37) -> 0 | D31: =SUM(D32:D37) -> 0 | E31: =D31-C31 -> 0
A32: Transferências intergovernamentais | E32: =D32-C32 -> 0
A33: Transferências de instituições privadas | E33: =D33-C33 -> 0
A34: Transferências do exterior | E34: =D34-C34 -> 0
A35: Transferências de pessoas | E35: =D35-C35 -> 0
A36: Transferências de convênios | E36: =D36-C36 -> 0
A37: Transferências para o combate à fome | E37: =D37-C37 -> 0
A38: OUTRAS RECEITAS CORRENTES | B38: =SUM(B39:B43) -> 0 | C38: =SUM(C39:C43) -> 0 | D38: =SUM(D39:D43) -> 0 | E38: =D38-C38 -> 0
A39: Multas e juros de mora | E39: =D39-C39 -> 0
A40: Indenizações e restituições | E40: =D40-C40 -> 0
A41: Receita da dívida ativa | E41: =D41-C41 -> 0
A42: Receitas decorrentes de aportes periódicos para amortização de déficit atuarial do RPPS | E42: =D42-C42 -> 0
A43: Receitas correntes diversas | E43: =D43-C43 -> 0
A44: RECEITAS DE CAPITAL | B44: =B45+B48+B51+B52+B60 -> 0 | C44: =C45+C48+C51+C52+C60 -> 0 | D44: =D45+D48+D51+D52+D60 -> 0 | E44: =D44-C44 -> 0
A45: OPERAÇÕES E CRÉDITO | B45: =SUM(B46:B47) -> 0 | C45: =SUM(C46:C47) -> 0 | D45: =SUM(D46:D47) -> 0 | E45: =D45-C45 -> 0
A46: Operações de crédito internas | E46: =D46-C46 -> 0
A47: Operações de crédito externas | E47: =D47-C47 -> 0
A48: ALIENAÇÃO DE BENS | B48: =SUM(B49:B50) -> 0 | C48: =SUM(C49:C50) -> 0 | D48: =SUM(D49:D50) -> 0 | E48: =D48-C48 -> 0
A49: Alienação de bens móveis | E49: =D49-C49 -> 0
A50: Alienação de bens imóveis | E50: =D50-C50 -> 0
A51: AMORTIZAÇÃO DE EMPRÉSTIMOS | E51: =D51-C51 -> 0
A52: TRANSFERÊNCIA DE CAPITAL | B52: =SUM(B53:B59) -> 0 | C52: =SUM(C53:C59) -> 0 | D52: =SUM(D53:D59) -> 0 | E52: =D52-C52 -> 0
A53: Transferências intergovernamentais | E53: =D53-C53 -> 0
A54: Transferências de instituições privadas | E54: =D54-C54 -> 0
A55: Transferências do exterior | E55: =D55-C55 -> 0
A56: Transferências de pessoas | E56: =D56-C56 -> 0
A57: Transferências de outras instituições públicas | E57: =D57-C57 -> 0
A58: Transferências de convênios | E58: =D58-C58 -> 0
A59: Transferências para o combate à fome | E59: =D59-C59 -> 0
A60: OUTRAS RECEITAS DE CAPITAL | B60: =SUM(B61:B64) -> 0 | C60: =SUM(C61:C64) -> 0 | D60: =SUM(D61:D64) -> 0 | E60: =D60-C60 -> 0
A61: Integralização de capital social | E61: =D61-C61 -> 0
A62: Dívida ativa proveniente da amortização de empréstimos e financiamentos | E62: =D62-C62 -> 0
A63: Restituições | E63: =D63-C63 -> 0
A64: Receitas de capital diversas | E64: =D64-C64 -> 0
A65: SUBTOTAL DAS RECEITAS (I) | B65: =B4+B44 -> 0 | C65: =C4+C44 -> 0 | D65: =D4+D44 -> 0 | E65: =D65-C65 -> 0
A66: REFINANCIAMENTO (II) | B66: =B67+B70 -> 0 | C66: =C67+C70 -> 0 | D66: =D67+D70 -> 0 | E66: =D66-C66 -> 0
A67: Operações de crédito internas | B67: =SUM(B68:B69) -> 0 | C67: =SUM(C68:C69) -> 0 | D67: =SUM(D68:D69) -> 0 | E67: =D67-C67 -> 0
A68: Mobiliária | E68: =D68-C68 -> 0
A69: Contratual | E69: =D69-C69 -> 0
A70: Operações de crédito externas | B70: =SUM(B71:B72) -> 0 | C70: =SUM(C71:C72) -> 0 | D70: =SUM(D71:D72) -> 0 | E70: =D70-C70 -> 0
A71: Mobiliária | E71: =D71-C71 -> 0
A72: Contratual | E72: =D72-C72 -> 0
A73: SUBTOTAL COM REFINANCIAMENTO (III = I+II) | B73: =B65+B66 -> 0 | C73: =C65+C66 -> 0 | D73: =D65+D66 -> 0 | E73: =D73-C73 -> 0
A74: DEFICIT (IV) | D74: =IF(D73<'BO-DESP'!D22,'BO-REC'!D73-'BO-DESP'!D22,0) -> 0
A75: TOTAL (V=III+IV) | B75: =B73+B74 -> 0 | C75: =C73+C74 -> 0 | D75: =D73+D74 -> 0
A76: SALDOS DE EXERCÍCIOS ANTERIORES (UTILIZADOS PARA CRÉDITOS ADICIONAIS) | D76: =SUM(D77:D78) -> 0
A77: Superávit financeiro
A78: Reabertura de créditos adicionais

Sheet BO-DESP
A1: BALANÇO ORÇAMENTÁRIO
A2: ='BO-REC'!A2 -> EXERCÍCIO DE 2015 | E2: ='BO-REC'!B2 -> DE 01/01/2015 A 31/12/2015
A3: DESPESAS ORÇAMENTÁRIAS | B3: DOTAÇÃO INICIAL (d) | C3: DOTAÇÃO ATUALIZADA (e) | D3: DESPESAS EMPENHADAS (f) | E3: DESPESAS LIQUIDADAS (g) | F3: DESPESAS PAGAS (h) | G3: SALDO DA DOTAÇÃO (i)=(e)-(f)
A4: DESPESAS CORRENTES | B4: =SUM(B5:B7) -> 0 | C4: =SUM(C5:C7) -> 0 | D4: =SUM(D5:D7) -> 0 | E4: =SUM(E5:E7) -> 0 | F4: =SUM(F5:F7) -> 0 | G4: =C4-D4 -> 0
A5: PESSOAL E ENCARGOS SOCIAIS | G5: =C5-D5 -> 0
A6: JUROS E ENCARGOS DA DÍVIDA | G6: =C6-D6 -> 0
A7: OUTRAS DESPESAS CORRENTES | G7: =C7-D7 -> 0
A8: DESPESAS DE CAPITAL | B8: =SUM(B9:B11) -> 0 | C8: =SUM(C9:C11) -> 0 | D8: =SUM(D9:D11) -> 0 | E8: =SUM(E9:E11) -> 0 | F8: =SUM(F9:F11) -> 0 | G8: =C8-D8 -> 0
A9: INVESTIMENTOS | G9: =C9-D9 -> 0
A10: INVERSÕES FINANCEIRAS | G10: =C10-D10 -> 0
A11: AMORTIZAÇÃO DA DÍVIDA | G11: =C11-D11 -> 0
A12: RESERVA DE CONTINGÊNCIA | G12: =C12-D12 -> 0
A13: RESERVA DO RPPS | G13: =C13-D13 -> 0
A14: SUBTOTAL DAS DESPESAS (VI) | B14: =B4+B8+B12+B13 -> 0 | C14: =C4+C8+C12+C13 -> 0 | D14: =D4+D8+D12+D13 -> 0 | E14: =E4+E8+E12+E13 -> 0 | F14: =F4+F8+F12+F13 -> 0 | G14: =C14-D14 -> 0
A15: AMORTIZAÇÃO DA DÍVIDA/REFINANCIAMENTO (VII) | B15: =B16+B19 -> 0 | C15: =C16+C19 -> 0 | D15: =D16+D19 -> 0 | E15: =E16+E19 -> 0 | F15: =F16+F19 -> 0 | G15: =C15-D15 -> 0
A16: Amortização da dívida interna | B16: =SUM(B17:B18) -> 0 | C16: =SUM(C17:C18) -> 0 | D16: =SUM(D17:D18) -> 0 | E16: =SUM(E17:E18) -> 0 | F16: =SUM(F17:F18) -> 0 | G16: =C16-D16 -> 0
A17: Dívida mobiliária | G17: =C17-D17 -> 0
A18: Outras dívidas | G18: =C18-D18 -> 0
A19: Amortização da dívida externa | B19: =SUM(B20:B21) -> 0 | C19: =SUM(C20:C21) -> 0 | D19: =SUM(D20:D21) -> 0 | E19: =SUM(E20:E21) -> 0 | F19: =SUM(F20:F21) -> 0 | G19: =C19-D19 -> 0
A20: Dívida mobiliária | G20: =C20-D20 -> 0
A21: Outras dívidas | G21: =C21-D21 -> 0
A22: SUBTOTAL COM REFINANCIAMENTO (VIII=VI+VII) | B22: =B14+B15 -> 0 | C22: =C14+C15 -> 0 | D22: =D14+D15 -> 0 | E22: =E14+E15 -> 0 | F22: =F14+F15 -> 0 | G22: =C22-D22 -> 0
A23: SUPERÁVIT (IX) | D23: =IF(D22<'BO-REC'!D73,'BO-REC'!D73-'BO-DESP'!D22,0) -> 0
A24: TOTAL (X=VIII+IX) | B24: =B22+B23 -> 0 | C24: =C22+C23 -> 0 | D24: =D22+D23 -> 0 | E24: =E22+E23 -> 0 | F24: =F22+F23 -> 0 | G24: =G22+G23 -> 0
A26: ANEXO I - DEMONTRATIVO DE EXECUÇÃO DOS RESTOS A PAGAR NÃO PROCESSADOS
A27: RESTOS A PAGAR NÃO PROCESSADOS | B27: INSCRITOS | D27: LIQUIDADOS (c) | E27: PAGOS (d) | F27: CANCELADOS (e) | G27: SALDO (f=a+b-d-e)
B28: EM EXERCÍCIOS ANTERIORES (a) | C28: EM 31 DE DEZ. DO EXERC. ANTERIOR (b)
A29: DESPESAS CORRENTES | B29: =SUM(B30:B32) -> 0 | C29: =SUM(C30:C32) -> 0 | D29: =SUM(D30:D32) -> 0 | E29: =SUM(E30:E32) -> 0 | F29: =SUM(F30:F32) -> 0 | G29: =B29+C29-E29-F29 -> 0
A30: PESSOAL E ENCARGOS SOCIAIS | G30: =B30+C30-E30-F30 -> 0
A31: JUROS E ENCARGOS DA DÍVIDA | G31: =B31+C31-E31-F31 -> 0
A32: OUTRAS DESPESAS CORRENTES | G32: =B32+C32-E32-F32 -> 0
A33: DESPESAS DE CAPITAL | B33: =SUM(B34:B36) -> 0 | C33: =SUM(C34:C36) -> 0 | D33: =SUM(D34:D36) -> 0 | E33: =SUM(E34:E36) -> 0 | F33: =SUM(F34:F36) -> 0 | G33: =B33+C33-E33-F33 -> 0
A34: INVESTIMENTOS | G34: =B34+C34-E34-F34 -> 0
A35: INVERSÕES FINANCEIRAS | G35: =B35+C35-E35-F35 -> 0
A36: AMORTIZAÇÃO DA DÍVIDA | G36: =B36+C36-E36-F36 -> 0
A37: TOTAL | B37: =B29+B33 -> 0 | C37: =C29+C33 -> 0 | D37: =D29+D33 -> 0 | E37: =E29+E33 -> 0 | F37: =F29+F33 -> 0 | G37: =B37+C37-E37-F37 -> 0
A39: ANEXO II - DEMONTRATIVO DE EXECUÇÃO DOS RESTOS A PAGAR PROCESSADOS E NÃO PROCESSADOS LIQUIDADOS
A40: RESTOS A PAGAR PROCESSADOS E NÃO PROCESSADOS LIQUIDADOS | B40: INSCRITOS | D40: PAGOS (c) | E40: CANCELADOS (d) | F40: SALDO (f=a+b-c-d)
B41: EM EXERCÍCIOS ANTERIORES (a) | C41: EM 31 DE DEZ. DO EXERC. ANTERIOR (b)
A42: DESPESAS CORRENTES | B42: =SUM(B43:B45) -> 0 | C42: =SUM(C43:C45) -> 0 | D42: =SUM(D43:D45) -> 0 | E42: =SUM(E43:E45) -> 0 | F42: =B42+C42-D42-E42 -> 0
A43: PESSOAL E ENCARGOS SOCIAIS | F43: =B43+C43-D43-E43 -> 0
A44: JUROS E ENCARGOS DA DÍVIDA | F44: =B44+C44-D44-E44 -> 0
A45: OUTRAS DESPESAS CORRENTES | F45: =B45+C45-D45-E45 -> 0
A46: DESPESAS DE CAPITAL | B46: =SUM(B47:B49) -> 0 | C46: =SUM(C47:C49) -> 0 | D46: =SUM(D47:D49) -> 0 | E46: =SUM(E47:E49) -> 0 | F46: =B46+C46-D46-E46 -> 0
A47: INVESTIMENTOS | F47: =B47+C47-D47-E47 -> 0
A48: INVERSÕES FINANCEIRAS | F48: =B48+C48-D48-E48 -> 0
A49: AMORTIZAÇÃO DA DÍVIDA | F49: =B49+C49-D49-E49 -> 0
A50: TOTAL | B50: =B42+B46 -> 0 | C50: =C42+C46 -> 0 | D50: =D42+D46 -> 0 | E50: =E42+E46 -> 0 | F50: =B50+C50-D50-E50 -> 0
A52: QUADRO I - RECEITAS INTRA-ORÇAMENTÁRIAS | B52: PREVISÃO INICIAL | C52: PREVISÃO ATUALIZADA (a) | D52: RECEITAS REALIZADAS (b) | E52: SALDO (c = b-a)
A53: RECEITAS CORRENTES INTRA-ORÇAMENTÁRIAS | B53: =B54+B59 -> 0 | C53: =C54+C59 -> 0 | D53: =D54+D59 -> 0 | E53: =D53-C53 -> 0
A54: RECEITA DE CONTRIBUIÇÕES INTRA-ORÇAMENTÁRIAS | B54: =B55 -> 0 | C54: =C55 -> 0 | D54: =D55 -> 0 | E54: =D54-C54 -> 0
A55: CONTRIBUIÇÕES PREVIDENCIÁRIAS DO REGIME PRÓPRIO INTRA-ORÇAMENTÁRIA | B55: =SUM(B56:B58) -> 0 | C55: =SUM(C56:C58) -> 0 | D55: =SUM(D56:D58) -> 0 | E55: =D55-C55 -> 0
A56: Contribuição patronal de servidor ativo | E56: =D56-C56 -> 0
A57: Contribuição previdenciária para amortização do déficit atuarial | E57: =D57-C57 -> 0
A58: Contribuição previdenciária em regime de parcelamento de débitos | E58: =D58-C58 -> 0
A59: OUTRAS RECEITAS CORRENTES INTRA-ORÇAMENTÁRIAS | B59: =B60 -> 0 | C59: =C60 -> 0 | D59: =D60 -> 0 | E59: =D59-C59 -> 0
A60: MULTA E JUROS DE MORA | B60: =B61 -> 0 | C60: =C61 -> 0 | D60: =D61 -> 0 | E60: =D60-C60 -> 0
A61: Multa e Juros de Mora das Contribuições | E61: =D61-C61 -> 0
A62: RECEITAS DE CAPITAL INTRA-ORÇAMENTÁRIAS | B62: =B63 -> 0 | C62: =C63 -> 0 | D62: =D63 -> 0 | E62: =D62-C62 -> 0
A63: ALIENAÇÃO DE BENS | B63: =B64 -> 0 | C63: =C64 -> 0 | D63: =D64 -> 0 | E63: =D63-C63 -> 0
A64: ALIENAÇÃO DE BENS MÓVEIS | B64: =B65 -> 0 | C64: =C65 -> 0 | D64: =D65 -> 0 | E64: =D64-C64 -> 0
A65: Receita de alienação de bens da saúde | E65: =D65-C65 -> 0
A66: TOTAL | B66: =B53+B62 -> 0 | C66: =C53+C62 -> 0 | D66: =D53+D62 -> 0 | E66: =D66-C66 -> 0
A68: QUADRO II - DESPESAS INTRA-ORÇAMENTÁRIAS | B68: DOTAÇÃO INICIAL (d) | C68: DOTAÇÃO ATUALIZADA (e) | D68: DESPESAS EMPENHADAS (f) | E68: DESPESAS LIQUIDADAS (g) | F68: DESPESAS PAGAS (h) | G68: SALDO DA DOTAÇÃO (i)=(e)-(f)
A69: DESPESAS CORRENTES INTRA-ORÇAMENTÁRIAS | B69: =B70 -> 0 | C69: =C70 -> 0 | D69: =D70 -> 0 | E69: =E70 -> 0 | F69: =F70 -> 0 | G69: =C69-D69 -> 0
A70: PESSOAL E ENCARGOS SOCIAIS | G70: =C70-D70 -> 0
A71: DESPESAS DE CAPITAL INTRA-ORÇAMENTÁRIAS | B71: =SUM(B72:B73) -> 0 | C71: =SUM(C72:C73) -> 0 | D71: =SUM(D72:D73) -> 0 | E71: =SUM(E72:E73) -> 0 | F71: =SUM(F72:F73) -> 0 | G71: =C71-D71 -> 0
A72: INVESTIMENTOS | G72: =C72-D72 -> 0
A73: AMORTIZAÇÃO DA DÍVIDA | G73: =C73-D73 -> 0
A74: TOTAL | B74: =B69+B71 -> 0 | C74: =C69+C71 -> 0 | D74: =D69+D71 -> 0 | E74: =E69+E71 -> 0 | F74: =F69+F71 -> 0 | G74: =C74-D74 -> 0
A76: QUADRO III - CRÉDITOS ADICIONAIS
A77: TIPO DE CRÉDITO | B77: CRÉDITO ADICIONAL | C77: ORIGEM DO RECURSO
C78: SUPERÁVIT | D78: EXCESSO DE ARRECADAÇÃO | E78: ANULAÇÃO DE DOTAÇÃO | F78: OP. CRÉDITO | G78: REABERTURA
A79: Crédito Suplementar
A80: Crédito Especial
A81: Crédito Extraordinário
A82: TOTAL | B82: =SUM(B79:B81) -> 0 | C82: =SUM(C79:C81) -> 0 | D82: =SUM(D79:D81) -> 0 | E82: =SUM(E79:E81) -> 0 | F82: =SUM(F79:F81) -> 0 | G82: =SUM(G79:G81) -> 0
A84: QUOCIENTE | G84: VALOR
A85: EQUILÍBRIO ORÇAMENTÁRIO: expressa a relação entre a previsão inicial da receita e a dotação inicial da despesa, indicando se há equilíbrio entre a previsão e fixação constante na LOA. | G85: ='BO-REC'!B65/'BO-DESP'!B24 -> #DIV/0!
A86: EXECUÇÃO DA RECEITA: demonstra a relação entre a receita realizada e a previsão atualizada da receita, indicando a existência de excesso ou falta de arrecadação para a cobertura de despesas. | G86: ='BO-REC'!D65/'BO-REC'!C65 -> #DIV/0!
A87: EXECUÇÃO DA RECEITA: demonstra a relação entre a receita realizada e a previsão inicial da receita, indicando a existência de excesso ou falta de arrecadação para administração dos indicadores fiscais. | G87: ='BO-REC'!D65/'BO-REC'!B65 -> #DIV/0!
A88: UTILIZAÇÃO DO EXCESSO DE ARRECADAÇÃO: resultante da relação dos créditos adicionais abertos por meio do excesso de arrecadação e o total do excesso de arrecadação, indicando a parcela do excesso de arrecadação utilizada para abertura de créditos adicionais. | G88: =IF(OR(D82=0,'BO-REC'!E73<=0),0,'BO-DESP'!D82/'BO-REC'!E73) -> 0
A89: UTILIZAÇÃO DO SUPERÁVIT FINANCEIRO: resultante da relação entre os créditos adicionais abertos por meio do superávit financeiro e o total do superávit financeiro apurado no exercício anterior, indicando a parcela do superávit financeiro utilizada para abertura de créditos adicionais. | G89: =IF(OR(C82=0,G51=0),0,G51/C82) -> 0
A90: EXECUÇÃO DA DESPESA: resultante da relação entre despesa executada e dotação atualizada, cuja discrepância pode ser ocasionada por ineficiência no processo planejamento-execução ou uma economia de despesa orçamentária. | G90: =D22/C22 -> #DIV/0!
A91: RESULTADO ORÇAMENTÁRIO: expressa a relação entre receita realizada e despesa empenhada, indicando a existência de superávit ou déficit. | G91: ='BO-REC'!D65/'BO-DESP'!D22 -> #DIV/0!
A92: EXECUÇÃO ORÇAMENTÁRIA CORRENTE: demonstra a relação entre a receita corrente realizada e a despesa corrente empenhada, indicando se a receita corrente suportou as despesas correntes ou se foi necessário utilizar receitas de capital para financiar despesas correntes. | G92: ='BO-REC'!D4/'BO-DESP'!D4 -> #DIV/0!
A93: FINANCEIRO REAL DA EXECUÇÃO: resultante da relação entre a receita realizada e a despesa paga, indicando o quanto a receita orçamentária arrecadada representa em relação à despesa orçamentária paga. | G93: ='BO-REC'!D65/'BO-DESP'!F22 -> #DIV/0!

Sheet BF
A1: BALANÇO FINANCEIRO
A2: ='BO-REC'!A2 -> EXERCÍCIO DE 2015 | D2: ='BO-REC'!B2 -> DE 01/01/2015 A 31/12/2015
A3: INGRESSOS | D3: DISPÊNDIOS
A4: ESPECIFICAÇÃO | B4: Exercício Atual | C4: Exercício Anterior | D4: ESPECIFICAÇÃO | E4: Exercício Atual | F4: Exercício Anterior
A5: Receita Orçamentária (I) | B5: =B6+B7+B13 -> 0 | C5: =C6+C7+C13 -> 0 | D5: Despesa Orçamentaria (VI) | E5: =E6+E7 -> 0 | F5: =F6+F7 -> 0
A6: Ordinária | D6: Ordinária
A7: Vinculada | B7: =SUM(B8:B12) -> 0 | C7: =SUM(C8:C12) -> 0 | D7: Vinculada | E7: =SUM(E8:E12) -> 0 | F7: =SUM(F8:F12) -> 0
A8: Previdência Social | D8: Previdência Social
A9: Destinadas à Saúde | D9: Destinadas à Saúde
A10: Destinadas à Educação | D10: Destinadas à Educação
A11: Destinadas à Assistência Social | D11: Destinadas à Assistência Social
A12: Outras receitas vinculadas | D12: Outras despesas vinculadas
D13: Pagamento de restos a pagar (VII)
A14: Transferências financeiras recebidas (II) | D14: Transferências financeiras concedidas (VIII)
A15: Recebimentos extraorçamentários (III) | D15: Pagamentos extraorçamentários (IX)
A16: Saldo em espécie do exercício anterior (IV) | D16: Saldo em espécie para o exercício seguinte (X)
A17: TOTAL (VI=I+II+III+IV+V) | B17: =B5+B14+B15+B16 -> 0 | C17: =C5+C14+C15+C16 -> 0 | D17: TOTAL (XII=VI+VII+VIII+IX+X+XI) | E17: =E5+E14+E15+E16+E13 -> 0 | F17: =F5+F14+F15+F16+F13 -> 0
A19: QUADRO I - RECEBIMENTOS E PAGAMENTOS EXTRAORÇAMENTÁRIOS
A20: RECEBIMENTOS | C20: VALOR | D20: PAGAMENTOS | F20: VALOR
A31: TOTAL | C31: =SUM(C21:C30) -> 0 | D31: TOTAL | F31: =SUM(F21:F30) -> 0
A33: QUADRO II - TRANSFERÊNCIAS FINANCEIRAS INTRA OFSS (EXCLUÍDAS DO BALANÇO FINANCEIRO CONSOLIDADO)
A34: TRANSFERÊNCIAS FINANCEIRAS RECEBIDAS | C34: VALOR | D34: TRANSFERÊNCIAS FINANCEIRAS CONCEDIDAS | E34: VALOR
A36: TOTAL | C36: =SUM(C35:C35) -> 0 | D36: =SUM(D35:D35) -> 0 | E36: =SUM(E35:E35) -> 0
A38: QUADRO III - DEDUÇÕES DAS RECEITAS ORÇAMENTÁRIAS
A39: NATUREZA DA DEDUÇÃO | E39: VALOR
A43: TOTAL | E43: =SUM(E40:E42) -> 0
A45: QUADRO IV - AJUSTES E PERDAS EM INVESTIMENTOS DO RPPS
A46: INVESTIMENTO | B46: SALDO 31/12/X-1 | C46: PROVISÃO | D46: REVERSÃO DA PROVISÃO | E46: SALDO 31/12/X | F46: PERDAS
A53: TOTAL | B53: =SUM(B47:B52) -> 0 | C53: =SUM(C47:C52) -> 0 | D53: =SUM(D47:D52) -> 0 | E53: =SUM(E47:E52) -> 0 | F53: =SUM(F47:F52) -> 0
A55: QUOCIENTES - BALANÇO FINANCEIRO
A56: QUOCIENTE | F56: VALOR
A57: ORÇAMENTÁRIO DO RESULTADO FINANCEIRO: resultante da relação entre o resultado orçamentário (receita orçamentária - despesa orçamentária) e a variação do saldo em espécie e indica a parcela da variação do saldo do disponível que pode ser explicada pelo resultado orçamentário. | F57: =('BO-REC'!D65-'BO-DESP'!D22)/(BF!E16-BF!B16) -> #DIV/0!
A58: RESULTADO DOS SALDOS FINANCEIROS: resultante da relação entre o saldo que passa para o exercício seguinte e o aldo do exercício anterior, indicando o impacto do resultado financeiro sobre o saldo em espécie. | F58: =E16/B16 -> #DIV/0!

Sheet DVP
A1: DEMONSTRAÇÃO DAS VARIAÇÕES PATRIMONIAIS
A2: ='BO-REC'!A2 -> EXERCÍCIO DE 2015 | B2: ='BO-REC'!B2:E2 -> DE 01/01/2015 A 31/12/2015
A3: VARIAÇÕES PATRIMONIAIS QUANTITATIVAS | B3: Exercício Atual | C3: Exercício Anterior
A4: VARIAÇÕES PATRIMONIAIS AUMENTATIVAS | B4: =B5+B9+B14+B18+B25+B34+B38 -> 0 | C4: =C5+C9+C14+C18+C25+C34+C38 -> 0
A5: Impostos, taxas e contribuições de melhoria | B5: =SUM(B6:B8) -> 0 | C5: =SUM(C6:C8) -> 0
A6: Impostos
A7: Taxas
A8: Contribuições de melhoria
A9: Contribuições | B9: =SUM(B10:B13) -> 0 | C9: =SUM(C10:C13) -> 0
A10: Contribuições sociais
A11: Contribuições de intervenção no domínio econômico
A12: Contribuição de iluminação pública
A13: Contribuição de interesse de categorias profissionais
A14: Exploração e venda de bens, serviços e direitos | B14: =SUM(B15:B17) -> 0 | C14: =SUM(C15:C17) -> 0
A15: Venda de mercadorias
A16: Venda de produtos
A17: Exploração de bens, direitos e prestação de serviços
A18: Variações patrimoniais aumentativas financeiras | B18: =SUM(B19:B24) -> 0 | C18: =SUM(C19:C24) -> 0
A19: Juros e encargos de empréstimos e financiamentos concedidos
A20: Juros e encargos de mora
A21: Variações monetárias e cambiais
A22: Descontos financeiros obtidos
A23: Remuneração de depósitos bancários e aplicações financeiras
A24: Outras variações aumentativas - financeiras
A25: Transferências e delegações recebidas | B25: =SUM(B26:B33) -> 0 | C25: =SUM(C26:C33) -> 0
A26: Transferências intragovernamentais
A27: Transferências intergovernamentais
A28: Transferências das instituições privadas
A29: Transferências das instituições multigovernamentais
A30: Transferências de consórcios públicos
A31: Transferências do exterior
A32: Delegações recebidas
A33: Transferências de pessoas físicas
A34: Valorização e ganhos com ativos | B34: =SUM(B35:B37) -> 0 | C34: =SUM(C35:C37) -> 0
A35: Reavaliação de ativos
A36: Ganhos com alienação
A37: Ganhos com incorporação de ativos por descobertas e nascimentos
A38: Outras variações patrimoniais aumentativas | B38: =SUM(B39:B42) -> 0 | C38: =SUM(C39:C42) -> 0
A39: Variação patrimonial aumentativa a classificar
A40: Resultado positivo de participações
A41: Reversão de provisões e ajustes de perdas
A42: Diversas variações patrimoniais aumentativas
A43: VARIAÇÕES PATRIMONIAIS DIMINUTIVAS | B43: =B44+B50+B57+B62+B68+B76+B80+B84 -> 0 | C43: =C44+C50+C57+C62+C68+C76+C80+C84 -> 0
A44: Pessoal e encargos | B44: =SUM(B45:B49) -> 0 | C44: =SUM(C45:C49) -> 0
A45: Remuneração a pessoal
A46: Encargos patronais
A47: Benefícios a pessoal
A48: Custo de pessoal e encargos
A49: Outras variações patrimoniais diminutivas - pessoal e encargos
A50: Benefícios previdenciários e assistenciais | B50: =SUM(B51:B56) -> 0 | C50: =SUM(C51:C56) -> 0
A51: Aposentadorias e reformas
A52: Pensões
A53: Benefícios de prestação continuada
A54: Benefícios eventuais
A55: Políticas públicas de transferência de renda
A56: Outros benefícios previdenciários e assistenciais
A57: Uso de bens, serviços e consumo de capital fixo | B57: =SUM(B58:B61) -> 0 | C57: =SUM(C58:C61) -> 0
A58: Uso de material de consumo
A59: Serviços
A60: Depreciação, amortização e exaustão
A61: Custo de materiais, serviços e consumo de capital fixo
A62: Variações patrimoniais diminutivas financeiras | B62: =SUM(B63:B67) -> 0 | C62: =SUM(C63:C67) -> 0
A63: Juros e encargos de empréstimos e financiamentos obtidos
A64: Juros e encargos de mora
A65: Variações monetárias e cambiais
A66: Descontos financeiros concedidos
A67: Outras variações patrimoniais diminutivas - financeiras
A68: Transferências e delegações concedidas | B68: =SUM(B69:B75) -> 0 | C68: =SUM(C69:C75) -> 0
A69: Transferências intragovernamentais
A70: Transferências intergovernamentais
A71: Transferências a instituições privadas
A72: Transferências a instituições multigovernamentais
A73: Transferências a consórcios públicos
A74: Transferências ao exterior
A75: Delegações concedidas
A76: Desvalorização e perda de ativos | B76: =SUM(B77:B79) -> 0 | C76: =SUM(C77:C79) -> 0
A77: Redução a valor recuperável e provisão para perdas
A78: Perdas com alienação
A79: Perdas involuntárias
A80: Tributárias | B80: =SUM(B81:B83) -> 0 | C80: =SUM(C81:C83) -> 0
A81: Impostos, taxas e contribuições de melhoria
A82: Contribuições
A83: Custo com tributos
A84: Outras variações patrimoniais diminutivas | B84: =SUM(B85:B92) -> 0 | C84: =SUM(C85:C92) -> 0
A85: Premiações
A86: Resultado negativo de participações
A87: Incentivos
A88: Subvenções econômicas
A89: Participações e contribuições
A90: VPD de constituição de provisões
A91: Custo de outras VPD
A92: Diversas variações patrimoniais diminutivas
A93: Resultado Patrimonial do período | B93: =B4-B43 -> 0 | C93: =C4-C43 -> 0
A94: VARIAÇÕES PATRIMONIAIS QUALITATIVAS (decorrentes da execução orçamentária)
A95: Incorporação de ativo
A96: Desincorporação de passivo
A97: Incorporação de passivo
A98: Desincorporação de ativo
A100: QUOCIENTES - DEMONSTRAÇÃO DAS VARIAÇÕES PATRIMONAIS
A101: QUOCIENTE | C101: VALOR
...

Sheet BP
A1: BALANÇO PATRIMONIAL
A2: ='BO-REC'!A2 -> EXERCÍCIO DE 2015 | D2: ='BO-REC'!B2 -> DE 01/01/2015 A 31/12/2015
A3: ATIVO | D3: PASSIVO
A4: ESPECIFICAÇÃO | B4: Exercício Atual | C4: Exercício Anterior | D4: ESPECIFICAÇÃO | E4: Exercício Atual | F4: Exercício Anterior
A5: ATIVO CIRCULANTE | B5: =SUM(B6:B7,B15:B18) -> 0 | C5: =SUM(C6:C7,C15:C18) -> 0 | D5: PASSIVO CIRCULANTE | E5: =SUM(E6:E12) -> 0 | F5: =SUM(F6:F12) -> 0
A6: Caixa e equivalentes de caixa | D6: Obrigações trabalhistas, previdenciárias e assistencias a pagar a curto prazo
A7: Créditos a curto prazo | B7: =SUM(B8:B14) -> 0 | C7: =SUM(C8:C14) -> 0 | D7: Emprestimos e financiamentos a curto prazo
A8: Clientes | D8: Fornecedores e contas a pagar a curto prazo
A9: Créditos tributários a receber | D9: Obrigações fiscais a curto prazo
A10: Dívida ativa tributária | D10: Obrigações de repartição a outros entes
A11: Dívida ativa não tributária - clientes | D11: Provisões a curto prazo
A12: Créditos de transferências a receber | D12: Demais obrigações a curto prazo
A13: Empréstimos e financiamentos concedidos
A14: (-) Ajuste de perdas de créditos a curto prazo
A15: Demais créditos e valores a curto prazo
A16: Investimentos e aplicações temporárias a curto prazo
A17: Estoques
A18: VPD pagas antecipadamente
A19: ATIVO NÃO-CIRCULANTE | B19: =B20+B32+B38 -> 0 | C19: =C20+C32+C38 -> 0 | D19: PASSIVO NÃO CIRCULANTE | E19: =SUM(E20:E27) -> 0 | F19: =SUM(F20:F27) -> 0
A20: Ativo realizável a longo prazo | B20: =SUM(B21,B28:B31) -> 0 | C20: =SUM(C21,C28:C31) -> 0 | D20: Obrigações trabalhistas, previdenciárias e assistencias a pagar a longo prazo
A21: Créditos a longo prazo | B21: =SUM(B22:B27) -> 0 | C21: =SUM(C22:C27) -> 0 | D21: Emprestimos e financiamentos a longo prazo
A22: Clientes | D22: Fornecedores a longo prazo
A23: Créditos tributários a receber | D23: Obrigações fiscais a longo prazo
A24: Dívida ativa tributária | D24: Obrigações de repartição a outros entes
A25: Dívida ativa não tributária - clientes | D25: Provisões a longo prazo
A26: Empréstimos e financiamentos concedidos | D26: Demais obrigações a longo prazo
A27: (-) Ajuste de perdas de créditos a curto prazo | D27: Resultado diferido
A28: Demais créditos e valores a longo prazo | D28: TOTAL DO PASSIVO | E28: =E5+E19 -> 0 | F28: =F5+F19 -> 0
A29: Investimentos e aplicações temporárias a longo prazo | D29: PATRIMÔNIO LÍQUIDO
A30: Estoques | D30: ESPECIFICAÇÃO | E30: Exercício Atual | F30: Exercício Anterior
A31: VPD pagas antecipadamente | D31: Patrimônio social e capital social
A32: Investimentos | B32: =SUM(B33,B36:B37) -> 0 | C32: =SUM(C33,C36:C37) -> 0 | D32: Adiantamento para futuro aumento de capital
A33: Participações permanentes | B33: =SUM(B34:B35) -> 0 | C33: =SUM(C34:C35) -> 0 | D33: Reservas de capital
A34: Participações avaliadas pelo método de equivalência patrimonial | D34: Ajustes de avaliação patrimonial
A35: Participações avaliadas pelo método de custo | D35: Reservas de lucros
A36: Propriedades para investimento | D36: Demais reservas
A37: Demais investimentos permanentes | D37: Resultados acumulados | E37: =SUM(E38:E40) -> 0 | F37: =SUM(F38:F40) -> 0
A38: Imobilizado | B38: =SUM(B39:B41) -> 0 | C38: =SUM(C39:C41) -> 0 | D38: Resultado do exercício
A39: Bens móveis | D39: Resultados de exercícios anteriores
A40: Bens imóveis | D40: Ajustes de exercícios anteriores
A41: Intangível | D41: (-) Ações/Cotas em tesouraria
A42: Softwares | D42: TOTAL DO PATRIMÔNIO LÍQUIDO | E42: =SUM(E31:E37,E41) -> 0 | F42: =SUM(F31:F37,F41) -> 0
A43: Marcas, direitos e patentes industrias
A44: Direito de uso de imóveis
A45: TOTAL | B45: =B19+B5 -> 0 | C45: =C19+C5 -> 0 | D45: TOTAL | E45: =E28+E42 -> 0 | F45: =F28+F42 -> 0
A47: ATIVO FINANCEIRO | D47: PASSIVO FINANCEIRO
A48: ATIVO PERMANENTE | D48: PASSIVO PERMANENTE
A49: SALDO PATRIMONIAL | E49: =B47+B48-E47-E48 -> 0 | F49: =C47+C48-F47-F48 -> 0
A50: SUPERÁVIT FINANCEIRO DO EXERCÍCIO | E50: =B47-E47 -> 0 | F50: =C47-F47 -> 0
A52: ANEXO I - COMPENSAÇÕES
A53: ESPECIFICAÇÃO | B53: Exercício Atual | C53: Exercício Anterior | D53: ESPECIFICAÇÃO | E53: Exercício Atual | F53: Exercício Anterior
A54: Saldo dos Atos Potenciais Ativos | D54: Saldo dos Atos Potenciais Passivos
A55: Direitos conveniados | D55: Obrigações conveniadas
A56: Direitos contratuais | D56: Obrigações contratuais
A57: Parcelamento de débitos previdenciários | D57: Outros atos potenciais passivos
A58: TOTAL | B58: =SUM(B55:B57) -> 0 | C58: =SUM(C55:C57) -> 0 | D58: TOTAL | E58: =SUM(E55:E57) -> 0 | F58: =SUM(F55:F57) -> 0
A60: ANEXO II - DEMONSTRATIVO DO SUPERÁVIT/DÉFICIT FINANCEIRO APURADO NO BALANÇO PATRIMONIAL
A61: DESTINAÇÃO DE RECURSOS | B61: SALDO BANCÁRIO | C61: RESTOS A PAGAR | D61: VALORES RESTITUÍVEIS | E61: OUTRAS DEDUÇÕES | F61: SUPERÁVIT FINANCEIRO
A62: 0001 LIVRE | F62: =B62-C62-D62-E62 -> 0
A63: 0020 MDE | F63: =B63-C63-D63-E63 -> 0
A64: 0040 ASPS | F64: =B64-C64-D64-E64 -> 0
A65: 0050 RPPS | F65: =B65-C65-D65-E65 -> 0
F66: =B66-C66-D66-E66 -> 0
F67: =B67-C67-D67-E67 -> 0
F68: =B68-C68-D68-E68 -> 0
F69: =B69-C69-D69-E69 -> 0
F70: =B70-C70-D70-E70 -> 0
F71: =B71-C71-D71-E71 -> 0
F72: =B72-C72-D72-E72 -> 0
F73: =B73-C73-D73-E73 -> 0
F74: =B74-C74-D74-E74 -> 0
F75: =B75-C75-D75-E75 -> 0
F76: =B76-C76-D76-E76 -> 0
F77: =B77-C77-D77-E77 -> 0
... F96: =B96-C96-D96-E96 -> 0
A97: TOTAL | B97: =SUM(B62:B96) -> 0 | C97: =SUM(C62:C96) -> 0 | D97: =SUM(D62:D96) -> 0 | E97: =SUM(E62:E96) -> 0 | F97: =SUM(F62:F96) -> 0
A99: QUADRO I - DETALHAMENTO DO ATIVO IMOBILIZADO
A100: ATIVO IMOBILIZADO | B100: SALDO BRUTO | C100: DEPRECIAÇÃO | D100: SALDO LÍQUIDO
A101: Máquinas, Aparelhos, Equipamentos e Ferramentas | D101: =B101-C101 -> 0
A102: Bens de Informática | D102: =B102-C102 -> 0
A103: Móveis e Utensílios | D103: =B103-C103 -> 0
A104: Materiais, Culturais, Educacionais e de Comunicação | D104: =B104-C104 -> 0
A105: Veículos | D105: =B105-C105 -> 0
A106: Terrenos/Glebas | D106: =B106-C106 -> 0
A107: Edifícios | D107: =B107-C107 -> 0
A108: Ruas | D108: =B108-C108 -> 0
A109: Praças | D109: =B109-C109 -> 0
A110: TOTAL | B110: =SUM(B101:B109) -> 0 | C110: =SUM(C101:C109) -> 0 | D110: =SUM(D101:D109) -> 0
A112: QUOCIENTES - BALANÇO PATRIMONIAL
A113: QUOCIENTE | F113: VALOR
A114: LIQUIDEZ IMEDIATA (Disponibilidades / Passivo Circulante): indica a capacidade financeira da entidade em honrar imediatamente seus compromissos de curto prazo contando apenas com suas disponibilidades, ou seja, os recursos disponíveis em caixa ou bancos. | F114: =IF(ISERR(B6/E5),0,B6/E5) -> 0
A115: LIQUIDEZ CORRENTE (Ativo Circulante / Passivo Circulante): a liquidez corrente demonstra quanto a entidade poderá dispor de recursos a curto prazo para pagar suas dívidas circulantes. | F115: =IF(ISERR(B5/E5),0,B5/E5) -> 0
A116: LIQUIDEZ SECA (Disponibilidades + Créditos a Curto Prazo / Passivo Circulante): demonstra quanto a entidade poderá dispor de recursos circulantes, sem levar em conta seus itens não monetários, como estoques e despesas antecipadas, para fazer face às uas obrigações de curto prazo. | F116: =IF(ISERR((B6+B7)/E5),0,(B6+B7)/E5) -> 0
A117: LIQUIDEZ GERAL (Ativo Circulante + Ativo Realizável a Longo Prazo / Passivo Circulante + Passivo Não Circulante): a liquidez geral ou índice de solvência geral é uma medida de capacidade da entidade em honrar todas as suas exigibilidades, contando, para isso, com seus recursos realizáveis a curto e longo prazos. | F117: =(B5+B20)/(E5+E19) -> #DIV/0!
A118: ÍNDICE DE SOLVÊNCIA (Ativo Circulante + Ativo Não Circulante / Passivo Circulante + Passivo Não Circulante): uma entidade é solvente quando está em condições de fazer frente a suas obrigações e ainda apresenta uma situação patrimonial que garanta sua sobrevivência no futuro. | F118: =(B5+B19)/(E5+E19) -> #DIV/0!
A119: ENDIVIDAMENTO GERAL (Passivo Circulante + Passivo Não Circulante / Ativo Total): esse índice demonstra o grau de endividamento da entidade e também reflete sua estrutura de capital. | F119: =(E5+E19)/B45 -> #DIV/0!
A120: COMPOSIÇÃO DO ENDIVIDAMENTO (Passivo Circulante / Passivo Circulante + Passivo Não Circulante): representa a parcela de curto prazo sobre a composição do endividamento total. | F120: =E5/(E5+E19) -> #DIV/0!

Sheet DFC
A1: DEMONSTRAÇÃO DOS FLUXOS DE CAIXA
A2: ='BO-REC'!A2 -> EXERCÍCIO DE 2015 | B2: ='BO-REC'!B2:E2 -> DE 01/01/2015 A 31/12/2015
A3: ESPECIFICAÇÃO | B3: Exercício Atual | C3: Exercício Anterior
A4: FLUXOS E CAIXA DAS ATIVIDADES DAS OPERAÇÕES
A5: INGRESSOS | B5: =B6+B10+B17+B24 -> 1668185.6 | C5: =C6+C10+C17 -> 0
A6: RECEITAS DERIVADAS | B6: =SUM(B7:B9) -> 0 | C6: =SUM(C7:C9) -> 0
A7: Receita tributária
A8: Receita de contribuições
A9: Outras receitas derivadas
A10: RECEITAS ORIGINÁRIAS | B10: =SUM(B11:B16) -> 0 | C10: =SUM(C11:C16) -> 0
A11: Receita patrimonial
A12: Receita agropecuária
A13: Receita industrial
A14: Receita de serviços
A15: Outras receitas originárias
A16: Remuneração das disponibilidades
A17: TRANSFERÊNCIAS | B17: =B18+B23+B22 -> 0 | C17: =C18+C23+C22 -> 0
A18: Intergovernamentais | B18: =SUM(B19:B21) -> 0 | C18: =SUM(C19:C21) -> 0
A19: da União
A20: de Estados e Distrito Federal
A21: de Municípios
A22: Multigovernamentais
A23: Intragovernamentais
A24: RECEBIMENTOS EXTRA-ORÇAMENTÁRIOS | B24: =1668198.07-12.48 -> 1668185.6
A25: DESEMBOLSOS | B25: =B26+B47+B51+B57 -> 0 | C25: =C26+C47+C51+C57 -> 0
A26: PESSOAL E OUTRAS DESPESAS CORRENTES POR FUNÇÃO | B26: =SUM(B27:B46) -> 0 | C26: =SUM(C27:C46) -> 0
A27: Legislativa
A28: Judiciária
A29: Administração
A30: Cultura
A31: Defesa nacional
A32: Desporto e lazer
A33: Encargos especiais
A34: Gestão ambiental
A35: Segurança pública
A36: Comércio e serviços
A37: Habitação
A38: Agricultura
... A46: Urbanismo
A47: JUROS E ENCARGOS DA DÍVIDA | B47: =SUM(B48:B50) -> 0 | C47: =SUM(C48:C50) -> 0
A48: Juros e correção monetária da dívida interna
A49: Juros e correção monetária da dívida externa
A50: Outros encargos da dívida
A51: TRANSFERÊNCIAS | B51: =B52+B56 -> 0 | C51: =C52+C56 -> 0
A52: Intergovernamentais | B52: =SUM(B53:B55) -> 0 | C52: =SUM(C53:C55) -> 0
A53: a União
A54: a Estados e Distrito Federal
A55: a Municípios
A56: Intragovernamentais
A57: PAGAMENTOS EXTRA-ORÇAMENTÁRIOS
A58: FLUXO DE CAIXA LÍQUIDO DAS ATIVIDADES DAS OPERAÇÕES | B58: =B5-B25 -> 1668185.6 | C58: =C5-C25 -> 0
A59: FLUXOS DE CAIXA DAS ATIVIDADES DE INVESTIMENTO
A60: INGRESSOS | B60: =SUM(B61:B63) -> 0 | C60: =SUM(C61:C63) -> 0
A61: ALIENAÇÃO DE BENS
A62: REVERSÃO DE PROVISÕES E AJUSTES DE PERDAS
A63: AMORTIZAÇÃO DE EMPRÉSTIMOS E FINANCIAMENTOS CONCEDIDOS
A64: DESEMBOLSOS | B64: =SUM(B65:B68) -> 0 | C64: =SUM(C65:C68) -> 0
A65: AQUISIÇÃO DE ATIVO NÃO CIRCULANTE
A66: CONCESSÃO DE EMPRÉSTIMOS E FINANCIAMENTOS
A67: CONSOLIDAÇÃO DE PERDAS EM INVESTIMENTOS
A68: PROVISÃO PARA PERDAS EM INVESTIMENTOS
A69: FLUXO DE CAIXA LÍQUIDO DAS ATIVIDADES DE INVESTIMENTO | B69: =B60-B64 -> 0 | C69: =C60-C64 -> 0
A70: FLUXOS DE CAIXA DAS ATIVIDADES DE FINANCIAMENTO
A71: INGRESSOS | B71: =B72 -> 0 | C71: =C72 -> 0
A72: OPERAÇÕES DE CRÉDITOS
A73: DESEMBOLSOS | B73: =B74 -> 0 | C73: =C74 -> 0
A74: AMORTIZAÇÃO/REFINANCIAMENTO DA DÍVIDA
A75: FLUXO DE CAIXA LÍQUIDO DAS ATIVIDADES DE FINANCIAMENTO | B75: =B71-B73 -> 0 | C75: =C71-C73 -> 0
A76: APURAÇÃO DO FLUXO DE CAIXA DO PERÍODO
A77: GERAÇÃO LÍQUIDA DE CAIXA E EQUIVALENTE DE CAIXA | B77: =B58+B69+B75 -> 1668185.6 | C77: =C58+C69+C75 -> 0
A78: CAIXA E EQUIVALENTE DE CAIXA INICIAL
A79: CAIXA E EQUIVALENTE DE CAIXA FINAL
A81: QUOCIENTES - DEMONSTRAÇÃO DAS VARIAÇÕES PATRIMONAIS
A82: QUOCIENTE | C82: VALOR
A83: FLUXO DE CAIXA OPERACIONAL LÍQUIDO EM RELAÇÃO AO RESULTADO PATRIMONIAL: resultante da relação entre o caixa líquido gerado nas operações e o resultado patrimonial, indicando a dispersão entre o fluxo de caixa operacional gerado e o resultado patrimonial do exercício. | C83: =B58/DVP!B93 -> #DIV/0!
A84: CAPACIDADE DE AMORTIZAÇÃO DA DÍVIDA: resultante da relação entre o caixa líquido gerado nas operações e o total do Passivo indicando a parcela dos recursos gerados pela entidade para o pagamento da dívida. | C84: =B58/(BP!E5+BP!E19) -> #DIV/0!
A85: ATIVIDADE OPERACIONAL: demonstra a relação entre o caixa líquido gerado das operações e o total da geração líquida de caixa indicando a parcela da geração líquida de caixa da entidade atribuída às atividades operacionais. | C85: =B58/B77 -> 1

Sheet Validação
A1: ITENS PARA VALIDAÇÃO DAS DCASP
A2: Valor 1 e Valor 2 sempre devem ser iguais
A3: ITEM 1 | B3: VALOR 1 | C3: ITEM 2 | D3: VALOR 2 | E3: DIFERENÇA
A4: Total de créditos especiais excluídas as reduções do BO | B4: ='BO-DESP'!B82-'BO-DESP'!E82 -> 0 | C4: Diferença entre dotação inicial e atualizada do BO | D4: ='BO-DESP'!C24-'BO-DESP'!B24 -> 0 | E4: =B4-D4 -> 0
A5: Total de superávit financeiro usado como origem de recursos para créditos adicionais do BO | B5: ='BO-DESP'!C82 -> 0 | C5: Superávit de saldos de exercícios anteriores do BO | D5: ='BO-REC'!D77 -> 0 | E5: =B5-D5 -> 0
A6: Total de reabertura usado como origem de recursos para créditos adicionais do BO | B6: ='BO-DESP'!G82 -> 0 | C6: Reabertura de saldos de exercícios anteriores do BO | D6: ='BO-REC'!D78 -> 0 | E6: =B6-D6 -> 0
A7: Receita orçamentária arrecadada do BO | B7: ='BO-REC'!D73 -> 0 | C7: Receita orçamentária do BF | D7: =BF!B5 -> 0 | E7: =B7-D7 -> 0
A8: Despesa orçamentária paga do BO | B8: ='BO-DESP'!F24 -> 0 | C8: Despesa orçamentária do BF | D8: =BF!E5 -> 0 | E8: =B8-D8 -> 0
A9: Saldo anterior do BF | B9: =BF!B16 -> 0 | C9: Saldo inicial da DFC | D9: =DFC!B78 -> 0 | E9: =B9-D9 -> 0
A10: Saldo final do BF | B10: =BF!E16 -> 0 | C10: Saldo final da DFC | D10: =DFC!B79 -> 0 | E10: =B10-D10 -> 0
A11: Saldo final do BF | B11: =BF!E16 -> 0 | C11: Caixa e equivalentes do BP + Investimentos BP | D11: =BP!B6+BP!B16 -> 0 | E11: =B11-D11 -> 0
A12: Recebimentos extraorçamentários do anexo do BF | B12: =BF!C31 -> 0 | C12: Recebimentos extraorçamentários do BF | D12: =BF!B15 -> 0 | E12: =B12-D12 -> 0
A13: Pagamentos extraorçamentários do anexo do BF | B13: =BF!F31 -> 0 | C13: Pagamentos extraorçamentários do BF | D13: =BF!E15 -> 0 | E13: =B13-D13 -> 0
A14: Resultado patrimonial da DVP | B14: =DVP!B93 -> 0 | C14: Resultado do exercício do BP | D14: =BP!E38 -> 0 | E14: =B14-D14 -> 0
A15: Caixa e equivalentes do BP + Investimentos BP | B15: =BP!B6+BP!B16 -> 0 | C15: Saldo final da DFC | D15: =DFC!B79 -> 0 | E15: =B15-D15 -> 0
A16: Superávit/déficit do anexo do BP | B16: =BP!F97 -> 0 | C16: Ativo Financeiro - Passivo financeiro | D16: =BP!B47-BP!E47 -> 0 | E16: =B16-D16 -> 0
