Workbook

Sheet Pessoal TCE
A1: ITEM | B1: CÓDIGO | C1: 42428 | D1: 42460 | E1: 42490 | F1: 42521 | G1: 42551 | H1: 42582 | I1: 42613 | J1: 42643 | K1: 42674 | L1: 42704 | M1: 42735 | N1: 42766 | O1: 42794 | P1: 42825 | Q1: 42855 | R1: 42886
A2: ÍNDICE | N2: =N4/N3 -> 0.48136984 | O2: =O4/O3 -> 0.47888258 | P2: =P4/P3 -> 0.47861148 | Q2: =Q4/Q3 -> 0.47706151 | R2: =R4/R3 -> 0.48355512
A3: RCL | N3: =SUM(C31:N31) -> 18319982 | O3: =SUM(D31:O31) -> 18381678 | P3: =SUM(E31:P31) -> 18521748 | Q3: =SUM(F31:Q31) -> 18676008 | R3: =SUM(G31:R31) -> 18524028
A4: DTP | N4: =SUM(C66:N66) -> 8818686.7 | O4: =SUM(D66:O66) -> 8802665.1 | P4: =SUM(E66:P66) -> 8864721.4 | Q4: =SUM(F66:Q66) -> 8909604.8 | R4: =SUM(G66:R66) -> 8957388.3
A6: Receitas Correntes | B6: 1.0.0.0.00.00.00.00.00 | C6: 1888341.4 | D6: 2020714.2 | E6: 2111521.5 | F6: 2210806.5 | G6: 1869631.4 | H6: 1854871.2 | I6: 1824460.2 | J6: 1605686.3 | K6: 1734366.8 | L6: 2176900.1 | M6: 3237842.8 | N6: 2057852.3 | O6: 2075445.1 | P6: 1923506.5 | Q6: 2020896 | R6: 2181027.2
A7: (-) Deduções da Receita Corrente | B7: 9.1.0.0.0.00.00.00.00.00 | C7: 235567.69 | D7: 229666.97 | E7: 245674.2 | F7: 308383.63 | G7: 214113.46 | H7: 183168.89 | I7: 252119.76 | J7: 174982.96 | K7: 207758.92 | L7: 402297.95 | M7: 358084.82 | N7: 269637 | O7: 235417.7 | P7: 230864.38 | Q7: 309960.74 | R7: 394207.07
A8: (-) Ativos / Inativos Poder Executivo / Indiretas | B8: 1.1.1.2.04.31.01.00.00 | C8: 26343.46 | D8: 22415.76 | E8: 22288.74 | F8: 21984.55 | G8: 30146.45 | H8: 24493.39 | I8: 21935.19 | J8: 20091.87 | K8: 21525 | L8: 22057.55 | M8: 55425.42 | N8: 32392.59 | O8: 22161.45 | P8: 24162.43 | Q8: 26176.01 | R8: 24941.18
A9: (-) Ativos / Inativos Poder Legislativo | B9: 1.1.1.2.04.31.02.00.00 | C9: 1466.33 | D9: 1272.34 | E9: 1272.34 | F9: 1273.78 | G9: 1670.93 | H9: 1458.58 | I9: 1286.3 | J9: 1184.58 | K9: 1173.56 | L9: 1097.33 | M9: 2507.39 | N9: 4902.18 | O9: 5737.02 | P9: 5090.05 | Q9: 4605.94 | R9: 4880.55
A10: (-) Multas e Juros de Mora do IRRF | B10: 1.9.1.1.02.03.00.00.00
A11: (-) Multas e Juros de Mora da Dívida Ativa do IRRF | B11: 1.9.1.3.02.03.00.00.00
A12: (-) Receita da Dívida Ativa do IRRF | B12: 1.9.3.1.01.03.00.00.00
A13: (-) Contribuição Social para o Financiamento da Seguridade Social | B13: 1.2.1.0.01.00.00.00.00
A14: (-) Contribuição para o RPPS do Servidor Público | B14: 1.2.1.0.29.00.00.00.00 | C14: 58907.16 | D14: 51795.63 | E14: 50454.9 | F14: 50889 | G14: 51080.58 | H14: 52155.46 | I14: 52921.44 | J14: 49980.16 | K14: 49885.88 | L14: 50379.04 | M14: 150878 | O14: 62131.75 | P14: 52958.68 | Q14: 52412.08 | R14: 53963.5
A15: (-) Compensações Financeiras Entre RGPS e RPPS | B15: 1.9.2.2.10.00.00.00.00
A16: (-) Remuneração dos Investimentos do RPPS | B16: 1.3.2.8.00.00.00.00.00 | C16: 240793.56 | D16: 448116.08 | E16: 361132.8 | F16: 75517.5 | G16: 192062.71 | H16: 258493.26 | I16: 180370.06 | J16: 188469.99 | K16: 110196.01 | L16: 70281.36 | M16: 293468.23 | N16: 239202.37 | O16: 389497.95 | P16: 166518.71 | Q16: 67259.44 | R16: 68789.05
A17: (-) Outras Receitas Diretamente Arrecadadas pelo RPPS | B17: 1.9.9.0.99.00.01.00.00
A18: (-) Receita de Rendimentos de Aplicações Financeiras - Fundo de Assistência Social do Servidor | B18: 1.3.2.5.01.99.02.00.00
A19: (-) Receitas Diretamente Arrecadadas pelo Fundo de Assistência Social dos Servidores | B19: 1.9.9.0.99.00.04.00.00
A20: (-) Receita de Rendimentos de Aplicações Financeiras - Fundo de Assistência à Saúde do Servidor | B20: 1.3.2.5.01.99.03.00.00
A21: (-) Receitas Diretamente Arrecadadas pelo Fundo de Assistência à Saúde dos Servidores | B21: 1.9.9.0.99.00.05.00.00
A22: (-) Outras Contribuições Sociais | B22: 1.2.1.0.99.00.00.00.00
A23: (+) Compensação Previdenciária à Prefeitura Municipal | B23: 1.2.1.0.99.00.10.00.00
A24: (+) Contribuição de Inativos e Pensionistas à Prefeitura Municipal | B24: 1.2.1.0.99.00.11.00.00
A25: (-) Multas e Juros de Mora das Contribuições ao RPPS | B25: 1.9.1.2.29.00.00.00.00
A26: (-) Multas e Juros de Mora de Outras Contribuições – Principal | B26: 1.9.1.2.99.01.00.00.00
A27: (-) Multas e Juros de Mora da Dívida Ativa das Contribuições | B27: 1.9.1.4.00.00.00.00.00
A28: (-) Receita da Dívida Ativa de Outras Contribuições | B28: 1.9.3.2.16.00.00.00.00
A29: (-) Transferência do FUNDEB | B29: 4.1.7.2.4.01.00.00.00.00 | C29: 183160.66 | D29: 200576.39 | E29: 223004.65 | F29: 209875.56 | G29: 179120.48 | H29: 174079.71 | I29: 183368.36 | J29: 177478.68 | K29: 184351.62 | L29: 209954.37 | M29: 236436.54 | N29: 257487.13 | O29: 158493.08 | P29: 237634.22 | Q29: 223763.6 | R29: 235991.32
A30: (+) Deduções para o FUNDEB (CP105) | B30: 9.1.0.0.0.00.00.00.00.00 | C30: =233542.69-108.74 -> 233433.95 | D30: 218784.62 | E30: 240276.24 | F30: 281790.04 | G30: 191710.22 | H30: 183168.89 | I30: 225916.26 | J30: 174982.96 | K30: 207758.92 | L30: 311141.1 | M30: 358084.82 | N30: 269386.11 | O30: 235226.2 | P30: 219448.41 | Q30: 265511.72 | R30: 274437.39
A31: RCL | C31: =C6-C7-C8-C9-C10-C11-C12-C13-C14-C15-C16-C17-C18-C19-C21-C22+C23+C24-C25-C26-C27-C28-C29+C30 -> 1375536.5 | D31: =D6-D7-D8-D9-D10-D11-D12-D13-D14-D15-D16-D17-D18-D19-D21-D22+D23+D24-D25-D26-D27-D28-D29+D30 -> 1285655.7 | E31: =E6-E7-E8-E9-E10-E11-E12-E13-E14-E15-E16-E17-E18-E19-E21-E22+E23+E24-E25-E26-E27-E28-E29+E30 -> 1447970.1 | F31: =F6-F7-F8-F9-F10-F11-F12-F13-F14-F15-F16-F17-F18-F19-F21-F22+F23+F24-F25-F26-F27-F28-F29+F30 -> 1824672.5 | G31: =G6-G7-G8-G9-G10-G11-G12-G13-G14-G15-G16-G17-G18-G19-G21-G22+G23+G24-G25-G26-G27-G28-G29+G30 -> 1393147 | H31: =H6-H7-H8-H9-H10-H11-H12-H13-H14-H15-H16-H17-H18-H19-H21-H22+H23+H24-H25-H26-H27-H28-H29+H30 -> 1344190.9 | I31: =I6-I7-I8-I9-I10-I11-I12-I13-I14-I15-I16-I17-I18-I19-I21-I22+I23+I24-I25-I26-I27-I28-I29+I30 -> 1358375.4 | J31: =J6-J7-J8-J9-J10-J11-J12-J13-J14-J15-J16-J17-J18-J19-J21-J22+J23+J24-J25-J26-J27-J28-J29+J30 -> 1168481 | ... R31: =R6-R7-R8-R9-R10-R11-R12-R13-R14-R15-R16-R17-R18-R19-R21-R22+R23+R24-R25-R26-R27-R28-R29+R30 -> 1672691.9
A33: Pessoal e Encargos Sociais (Despesa Liquidada) | B33: 3.1.00.00.00.00.00.00 | C33: 941958.32 | D33: 886171.77 | E33: 918230.04 | F33: 898260.19 | G33: 956724.37 | H33: 939481.07 | I33: 896084.58 | J33: 886644.39 | K33: 893153.53 | L33: 905781.73 | M33: 1858460.6 | N33: 1025828.6 | O33: 934960.01 | P33: 970645.32 | Q33: 1020434.3 | R33: 988723.72
A34: (-) Aposentadorias do RPPS, Reserva Remunerada e Reformas dos Militares (RV0050) | B34: 3.1.90.01.00.00.00.00 | C34: 81897.21 | D34: 79860.1 | E34: 79860.1 | F34: 79860.1 | G34: 79860.1 | H34: 80625.97 | I34: 78832.16 | J34: 78540.98 | K34: 75799.76 | L34: 75799.76 | M34: 152213.67 | N34: 82824.31 | O34: 82824.31 | P34: 82202.87 | Q34: 86124.51 | R34: 88692.86
A35: (-) Pensões do RPPS e do Militar (RV0050) | B35: 3.1.90.03.00.00.00.00 | C35: 30454.21 | D35: 30334.38 | E35: 30334.38 | F35: 30334.38 | G35: 30744.31 | H35: 37678.09 | I35: 40827.04 | J35: 41332.78 | K35: 42512.54 | L35: 42512.54 | M35: 77974.78 | N35: 45263.16 | O35: 45263.16 | P35: 43405.23 | Q35: 42823.47 | R35: 42823.47
A36: (-) Outros Benefícios Previdenciários – Pessoal Ativo (RV0050) | B36: 3.1.90.05.00.01.00.00 | C36: 38302.58 | D36: 29505 | E36: 25412.26 | F36: 29697.23 | G36: 32661 | H36: 42799.24 | I36: 39709.75 | J36: 39633.27 | K36: 37058.53 | L36: 39182.34 | M36: 77667.85 | N36: 38181.62 | O36: 30263.69 | P36: 37743.1 | Q36: 37630.52 | R36: 41529.22
A37: (-) Outros Benefícios Previdenciários – Pessoal Inativo (RV0050) | B37: 3.1.90.05.00.02.00.00
A38: (-) Outros Benefícios Previdenciários – Pensionistas (RV0050) | B38: 3.1.90.05.00.03.00.00
A39: (-) Outros Benefícios Assistenciais do Servidor e do Militar (RV0050) | B39: 3.1.90.08.00.00.00.00
A40: (-) Abono de Permanência | B40: 3.1.90.11.07.00.00.00
A41: (-) Licença-Prêmio Indenizada | B41: 3.1.90.11.48.00.00.00
A42: (-) Representação Mensal | B42: 3.1.90.11.75.00.00.00
A43: (-) INSS Sobre Sessão Extraordinária - Agentes Políticos | B43: 3.1.90.13.02.04.00.00
A44: (-) INSS Sobre Convocação Extraordinária - Agentes Políticos | B44: 3.1.90.13.02.05.00.00
A45: (-) Convocação Extraordinária | B45: 3.1.90.16.04.00.00.00
A46: (-) Ajuda de Custo | B46: 3.1.90.16.99.01.00.00
A47: (-) Remoções | B47: 3.1.90.16.99.02.00.00
A48: (-) Sessões Extraordinárias | B48: 3.1.90.16.99.03.00.00
... A52: (-) Gratificação por Tempo de Serviço - Anuênio - Pensionista Civil | B52: 3.1.90.92.25.00.00.00
A53: (-) Indenizações e Restituições Trabalhistas | B53: 3.1.90.94.00.00.00.00 | Q53: 14248 | R53: 0
A54: (-) Contribuições Patronais para o RPPS – Pensionista | B54: 3.1.91.13.03.03.00.00
A55: (-) Plano de Seguridade Social do Servidor - Pessoal Ativo | B55: 3.1.91.13.08.00.00.00
A56: (-) Plano de Seguridade Social do Servidor - Pessoal Inativo | B56: 3.1.91.13.10.00.00.00
A57: (-) Plano de Seguridade Social do Pensionista | B57: 3.1.91.13.12.00.00.00
A58: (-) Amortização do Passivo Atuarial com RPPS - Alíquota Suplementar | B58: 3.1.91.13.99.01.00.00 | C58: 67893.06 | D58: 66424.54 | E58: 66845.63 | F58: 66838.83 | G58: 68518.53 | H58: 69398.32 | I58: 65516.02 | J58: 65341.5 | K58: 65966.65 | L58: 65653.96 | M58: 131290.84 | N58: 87004.06 | O58: 73401.13 | P58: 63443.41 | Q58: 75059.49 | R58: 73408.34
A59: (-) IRRF Sobre o Rendimento do Trabalho – Ativos /Inativos do Poder Executivo/Indiretas | B59: 1.1.1.2.04.31.01.00.00 | C59: =C8 -> 26343.46 | D59: =D8 -> 22415.76 | E59: =E8 -> 22288.74 | F59: =F8 -> 21984.55 | G59: =G8 -> 30146.45 | H59: =H8 -> 24493.39 | I59: =I8 -> 21935.19 | J59: =J8 -> 20091.87 | ... R59: =R8 -> 24941.18
A60: (-) Multas e Juros de Mora do IRRF | B60: 1.9.1.1.02.03.00.00.00 | C60: =C10 -> 0 | D60: =D10 -> 0 | E60: =E10 -> 0 | F60: =F10 -> 0 | G60: =G10 -> 0 | H60: =H10 -> 0 | I60: =I10 -> 0 | J60: =J10 -> 0 | ... R60: =R10 -> 0
A61: (-) Multas e Juros de Mora da Dívida Ativa do IRRF | B61: 1.9.1.3.02.03.00.00.00 | C61: =C11 -> 0 | D61: =D11 -> 0 | E61: =E11 -> 0 | F61: =F11 -> 0 | G61: =G11 -> 0 | H61: =H11 -> 0 | I61: =I11 -> 0 | J61: =J11 -> 0 | ... R61: =R11 -> 0
A62: (-) Receita da Dívida Ativa do IRRF | B62: 1.9.3.1.01.03.00.00.00 | C62: =C12 -> 0 | D62: =D12 -> 0 | E62: =E12 -> 0 | F62: =F12 -> 0 | G62: =G12 -> 0 | H62: =H12 -> 0 | I62: =I12 -> 0 | J62: =J12 -> 0 | ... R62: =R12 -> 0
A63: (+) Recursos para Cobertura de Insuficiências Financeiras – Contas Patrimoniais | B63: 3.5.1.3.2.01.01.00.00.00
A64: (+) Recurso para Cobertura de Déficit Financeiro – Contas Patrimoniais | B64: 3.5.1.3.2.02.01.00.00.00
A65: (-) Contas de Controle de Consórcios – Saldo Credor ao final de cada bimestre | B65: 8.5.3.2.4.02.00.00.00.00 | D65: 0 | F65: 0 | G65: 1427.99 | H65: 0 | I65: 1332.98 | J65: 0 | L65: 0 | M65: 1452.2 | N65: 0 | O65: 0 | P65: 0 | Q65: 0 | R65: 0
A66: DTP | C66: =C33-C34-C35-C36-C37-C38-C39-C40-C41-C42-C43-C44-C45-C46-C47-C48-C49-C50-C51-C52-C53-C54-C55-C56-C57-C58-C59-C60-C61-C62+C63+C64-C65 -> 697067.8 | D66: =D33-D34-D35-D36-D37-D38-D39-D40-D41-D42-D43-D44-D45-D46-D47-D48-D49-D50-D51-D52-D53-D54-D55-D56-D57-D58-D59-D60-D61-D62+D63+D64-D65 -> 657631.99 | E66: =E33-E34-E35-E36-E37-E38-E39-E40-E41-E42-E43-E44-E45-E46-E47-E48-E49-E50-E51-E52-E53-E54-E55-E56-E57-E58-E59-E60-E61-E62+E63+E64-E65 -> 693488.93 | F66: =F33-F34-F35-F36-F37-F38-F39-F40-F41-F42-F43-F44-F45-F46-F47-F48-F49-F50-F51-F52-F53-F54-F55-F56-F57-F58-F59-F60-F61-F62+F63+F64-F65 -> 669545.1 | G66: =G33-G34-G35-G36-G37-G38-G39-G40-G41-G42-G43-G44-G45-G46-G47-G48-G49-G50-G51-G52-G53-G54-G55-G56-G57-G58-G59-G60-G61-G62+G63+G64-G65 -> 713365.99 | H66: =H33-H34-H35-H36-H37-H38-H39-H40-H41-H42-H43-H44-H45-H46-H47-H48-H49-H50-H51-H52-H53-H54-H55-H56-H57-H58-H59-H60-H61-H62+H63+H64-H65 -> 684486.06 | I66: =I33-I34-I35-I36-I37-I38-I39-I40-I41-I42-I43-I44-I45-I46-I47-I48-I49-I50-I51-I52-I53-I54-I55-I56-I57-I58-I59-I60-I61-I62+I63+I64-I65 -> 647931.44 | J66: =J33-J34-J35-J36-J37-J38-J39-J40-J41-J42-J43-J44-J45-J46-J47-J48-J49-J50-J51-J52-J53-J54-J55-J56-J57-J58-J59-J60-J61-J62+J63+J64-J65 -> 641703.99 | ... R66: =R33-R34-R35-R36-R37-R38-R39-R40-R41-R42-R43-R44-R45-R46-R47-R48-R49-R50-R51-R52-R53-R54-R55-R56-R57-R58-R59-R60-R61-R62+R63+R64-R65 -> 717328.65

Sheet Pessoal STN
A1: ITEM | B1: CÓDIGO | C1: 42428 | D1: 42460 | E1: 42490 | F1: 42521 | G1: 42551 | H1: 42582 | I1: 42613 | J1: 42643 | K1: 42674 | L1: 42704 | M1: 42735 | N1: 42766 | O1: 42794 | P1: 42825 | Q1: 42855 | R1: 42886
A2: ÍNDICE | N2: =N4/N3 -> 0.48126811 | O2: =O4/O3 -> 0.47635697 | P2: =P4/P3 -> 0.48152989 | Q2: =Q4/Q3 -> 0.48791038 | R2: =R4/R3 -> 0.49348943
A3: RCL | N3: =SUM(C15:N15) -> 20842211 | O3: =SUM(D15:O15) -> 21026240 | P3: =SUM(E15:P15) -> 20926672 | Q3: =SUM(F15:Q15) -> 20769803 | R3: =SUM(G15:R15) -> 20651126
A4: DTP | N4: =SUM(C28:N28) -> 10030692 | O4: =SUM(D28:O28) -> 10015996 | P4: =SUM(E28:P28) -> 10076818 | Q4: =SUM(F28:Q28) -> 10133803 | R4: =SUM(G28:R28) -> 10191112
A6: Receitas Correntes | B6: 1.0.0.0.00.00.00.00.00 | C6: ='Pessoal TCE'!C6 -> 1888341.4 | D6: ='Pessoal TCE'!D6 -> 2020714.2 | E6: ='Pessoal TCE'!E6 -> 2111521.5 | F6: ='Pessoal TCE'!F6 -> 2210806.5 | G6: ='Pessoal TCE'!G6 -> 1869631.4 | H6: ='Pessoal TCE'!H6 -> 1854871.2 | I6: ='Pessoal TCE'!I6 -> 1824460.2 | J6: ='Pessoal TCE'!J6 -> 1605686.3 | ... R6: ='Pessoal TCE'!R6 -> 2181027.2
A7: (-) Deduções da Receita Corrente | B7: 9.1.0.0.0.00.00.00.00.00 | C7: ='Pessoal TCE'!C7 -> 235567.69 | D7: ='Pessoal TCE'!D7 -> 229666.97 | E7: ='Pessoal TCE'!E7 -> 245674.2 | F7: ='Pessoal TCE'!F7 -> 308383.63 | G7: ='Pessoal TCE'!G7 -> 214113.46 | H7: ='Pessoal TCE'!H7 -> 183168.89 | I7: ='Pessoal TCE'!I7 -> 252119.76 | J7: ='Pessoal TCE'!J7 -> 174982.96 | ... R7: ='Pessoal TCE'!R7 -> 394207.07
A8: CONTRIBUIÇÃO DO SERVIDOR ATIVO CIVIL PARA O REGIME PRÓPRIO | B8: 1.2.1.0.29.07.00.00.00 | C8: ='Pessoal TCE'!C14 -> 58907.16 | D8: ='Pessoal TCE'!D14 -> 51795.63 | E8: ='Pessoal TCE'!E14 -> 50454.9 | F8: ='Pessoal TCE'!F14 -> 50889 | G8: ='Pessoal TCE'!G14 -> 51080.58 | H8: ='Pessoal TCE'!H14 -> 52155.46 | I8: ='Pessoal TCE'!I14 -> 52921.44 | J8: ='Pessoal TCE'!J14 -> 49980.16 | ... R8: ='Pessoal TCE'!R14 -> 53963.5
A9: CONTRIBUIÇÕES DO SERVIDOR INATIVO CIVIL PARA O REGIME PRÓPRIO | B9: 1.2.1.0.29.09.00.00.00
A10: CONTRIBUIÇÕES DE PENSIONISTA CIVIL PARA O REGIME PRÓPRIO | B10: 1.2.1.0.29.11.00.00.00
A11: MULTAS E JUROS DE MORA DAS COMPENSAÇÕES FINANCEIRAS ENTRE O REGIME GERAL E OS REGIMES PRÓPRIOS DE PR | B11: 1.9.1.2.56.00.00.00.00
A12: MULTAS E JUROS DE MORA DA DÍVIDA ATIVA DAS COMPENSAÇÕES FINANCEIRAS ENTRE O REGIME GERAL E OS REGIME | B12: 1.9.1.5.19.00.00.00.00
A13: COMPENSAÇÕES FINANCEIRAS ENTRE O REGIME GERAL E OS REGIMES PRÓPRIOS DE PREVIDÊNCIA DOS SERVIDORES | B13: 1.9.2.2.10.00.00.00.00
A14: RECEITA DA DÍVIDA ATIVA DAS COMPENSAÇÕES FINANCEIRAS ENTRE O REGIME GERAL E OS REGIMES PRÓPRIOS DE P | B14: 1.9.3.2.35.00.00.00.00
A15: RCL | C15: =C6-C7-C8-C9-C10-C11-C12-C13-C14 -> 1593866.6 | D15: =D6-D7-D8-D9-D10-D11-D12-D13-D14 -> 1739251.6 | E15: =E6-E7-E8-E9-E10-E11-E12-E13-E14 -> 1815392.4 | F15: =F6-F7-F8-F9-F10-F11-F12-F13-F14 -> 1851533.9 | G15: =G6-G7-G8-G9-G10-G11-G12-G13-G14 -> 1604437.3 | H15: =H6-H7-H8-H9-H10-H11-H12-H13-H14 -> 1619546.9 | I15: =I6-I7-I8-I9-I10-I11-I12-I13-I14 -> 1519419.1 | J15: =J6-J7-J8-J9-J10-J11-J12-J13-J14 -> 1380723.2 | ... R15: =R6-R7-R8-R9-R10-R11-R12-R13-R14 -> 1732856.6
A17: Pessoal e Encargos Sociais (Despesa Liquidada) | B17: 3.1.00.00.00.00.00.00 | C17: ='Pessoal TCE'!C33 -> 941958.32 | D17: ='Pessoal TCE'!D33 -> 886171.77 | E17: ='Pessoal TCE'!E33 -> 918230.04 | F17: ='Pessoal TCE'!F33 -> 898260.19 | G17: ='Pessoal TCE'!G33 -> 956724.37 | H17: ='Pessoal TCE'!H33 -> 939481.07 | I17: ='Pessoal TCE'!I33 -> 896084.58 | J17: ='Pessoal TCE'!J33 -> 886644.39 | ... R17: ='Pessoal TCE'!R33 -> 988723.72
A18: (+) Contratos de Terceirização | B18: 3.3.XX.34.00.00.00.00
A19: (-) Aposentadorias do RPPS, Reserva Remunerada e Reformas dos Militares (RV0050) | B19: 3.1.90.01.00.00.00.00 | C19: ='Pessoal TCE'!C34 -> 81897.21 | D19: ='Pessoal TCE'!D34 -> 79860.1 | E19: ='Pessoal TCE'!E34 -> 79860.1 | F19: ='Pessoal TCE'!F34 -> 79860.1 | G19: ='Pessoal TCE'!G34 -> 79860.1 | H19: ='Pessoal TCE'!H34 -> 80625.97 | I19: ='Pessoal TCE'!I34 -> 78832.16 | J19: ='Pessoal TCE'!J34 -> 78540.98 | ... R19: ='Pessoal TCE'!R34 -> 88692.86
A20: (-) Pensões do RPPS e do Militar (RV0050) | B20: 3.1.90.03.00.00.00.00 | C20: ='Pessoal TCE'!C35 -> 30454.21 | D20: ='Pessoal TCE'!D35 -> 30334.38 | E20: ='Pessoal TCE'!E35 -> 30334.38 | F20: ='Pessoal TCE'!F35 -> 30334.38 | G20: ='Pessoal TCE'!G35 -> 30744.31 | H20: ='Pessoal TCE'!H35 -> 37678.09 | I20: ='Pessoal TCE'!I35 -> 40827.04 | J20: ='Pessoal TCE'!J35 -> 41332.78 | ... R20: ='Pessoal TCE'!R35 -> 42823.47
A21: (-) Outros Benefícios Previdenciários – Pessoal Ativo (RV0050) | B21: 3.1.90.05.00.01.00.00 | C21: ='Pessoal TCE'!C36 -> 38302.58 | D21: ='Pessoal TCE'!D36 -> 29505 | E21: ='Pessoal TCE'!E36 -> 25412.26 | F21: ='Pessoal TCE'!F36 -> 29697.23 | G21: ='Pessoal TCE'!G36 -> 32661 | H21: ='Pessoal TCE'!H36 -> 42799.24 | I21: ='Pessoal TCE'!I36 -> 39709.75 | J21: ='Pessoal TCE'!J36 -> 39633.27 | ... R21: ='Pessoal TCE'!R36 -> 41529.22
A22: (-) Outros Benefícios Previdenciários – Pessoal Inativo (RV0050) | B22: 3.1.90.05.00.02.00.00 | C22: ='Pessoal TCE'!C37 -> 0 | D22: ='Pessoal TCE'!D37 -> 0 | E22: ='Pessoal TCE'!E37 -> 0 | F22: ='Pessoal TCE'!F37 -> 0 | G22: ='Pessoal TCE'!G37 -> 0 | H22: ='Pessoal TCE'!H37 -> 0 | I22: ='Pessoal TCE'!I37 -> 0 | J22: ='Pessoal TCE'!J37 -> 0 | ... R22: ='Pessoal TCE'!R37 -> 0
A23: (-) Outros Benefícios Previdenciários – Pensionistas (RV0050) | B23: 3.1.90.05.00.03.00.00 | C23: ='Pessoal TCE'!C38 -> 0 | D23: ='Pessoal TCE'!D38 -> 0 | E23: ='Pessoal TCE'!E38 -> 0 | F23: ='Pessoal TCE'!F38 -> 0 | G23: ='Pessoal TCE'!G38 -> 0 | H23: ='Pessoal TCE'!H38 -> 0 | I23: ='Pessoal TCE'!I38 -> 0 | J23: ='Pessoal TCE'!J38 -> 0 | ... R23: ='Pessoal TCE'!R38 -> 0
A24: (-) Outros Benefícios Assistenciais do Servidor e do Militar (RV0050) | B24: 3.1.90.08.00.00.00.00 | C24: ='Pessoal TCE'!C39 -> 0 | D24: ='Pessoal TCE'!D39 -> 0 | E24: ='Pessoal TCE'!E39 -> 0 | F24: ='Pessoal TCE'!F39 -> 0 | G24: ='Pessoal TCE'!G39 -> 0 | H24: ='Pessoal TCE'!H39 -> 0 | I24: ='Pessoal TCE'!I39 -> 0 | J24: ='Pessoal TCE'!J39 -> 0 | ... R24: ='Pessoal TCE'!R39 -> 0
A25: (-) Decisão Judicial de período anterior | B25: 3.1.XX.91.00.00.00.00
A26: (-) Despesas de competência anterior | B26: 3.1.XX.92.00.00.00.00
A27: (-) Indenização Trabalhista | B27: 3.1.XX.94.00.00.00.00 | C27: ='Pessoal TCE'!C53 -> 0 | D27: ='Pessoal TCE'!D53 -> 0 | E27: ='Pessoal TCE'!E53 -> 0 | F27: ='Pessoal TCE'!F53 -> 0 | G27: ='Pessoal TCE'!G53 -> 0 | H27: ='Pessoal TCE'!H53 -> 0 | I27: ='Pessoal TCE'!I53 -> 0 | J27: ='Pessoal TCE'!J53 -> 0 | ... R27: ='Pessoal TCE'!R53 -> 0
A28: DTP | C28: =C17-C18-C19-C20-C21-C22-C23-C24-C25-C26-C27 -> 791304.32 | D28: =D17-D18-D19-D20-D21-D22-D23-D24-D25-D26-D27 -> 746472.29 | E28: =E17-E18-E19-E20-E21-E22-E23-E24-E25-E26-E27 -> 782623.3 | F28: =F17-F18-F19-F20-F21-F22-F23-F24-F25-F26-F27 -> 758368.48 | G28: =G17-G18-G19-G20-G21-G22-G23-G24-G25-G26-G27 -> 813458.96 | H28: =H17-H18-H19-H20-H21-H22-H23-H24-H25-H26-H27 -> 778377.77 | I28: =I17-I18-I19-I20-I21-I22-I23-I24-I25-I26-I27 -> 736715.63 | J28: =J17-J18-J19-J20-J21-J22-J23-J24-J25-J26-J27 -> 727137.36 | ... R28: =R17-R18-R19-R20-R21-R22-R23-R24-R25-R26-R27 -> 815678.17
